{"1":{"4":{"5":{"x":4,"y":"1","z":"5","hex":"#5c5050","rgb":[92,80,80],"name":"Gravel","mat_id":"28","file":"textures\/13_0.png","transparent":false,"opacity":1,"texture":"13_0.png"},"4":{"x":4,"y":"1","z":"4","hex":"#78543f","rgb":[120,84,63],"name":"Dirt","mat_id":"15","file":"textures\/3_0.png","transparent":false,"opacity":1,"texture":"3_0.png"},"3":{"x":4,"y":"1","z":"3","hex":"#78543f","rgb":[120,84,63],"name":"Dirt","mat_id":"15","file":"textures\/3_0.png","transparent":false,"opacity":1,"texture":"3_0.png"},"2":{"x":4,"y":"1","z":"2","hex":"#78543f","rgb":[120,84,63],"name":"Dirt","mat_id":"15","file":"textures\/3_0.png","transparent":false,"opacity":1,"texture":"3_0.png"},"1":{"x":4,"y":"1","z":"1","hex":"#5c5050","rgb":[92,80,80],"name":"Gravel","mat_id":"28","file":"textures\/13_0.png","transparent":false,"opacity":1,"texture":"13_0.png"}},"14":{"3":{"x":14,"y":"1","z":"3","hex":"#78543f","rgb":[120,84,63],"name":"Dirt","mat_id":"15","file":"textures\/3_0.png","transparent":false,"opacity":1,"texture":"3_0.png"},"4":{"x":14,"y":"1","z":"4","hex":"#7a3d3d","rgb":[122,61,61],"name":"Coarse Dirt","mat_id":"16","file":"textures\/3_1.png","transparent":false,"opacity":1,"texture":"3_1.png"},"5":{"x":14,"y":"1","z":"5","hex":"#5c5050","rgb":[92,80,80],"name":"Gravel","mat_id":"28","file":"textures\/13_0.png","transparent":false,"opacity":1,"texture":"13_0.png"},"2":{"x":14,"y":"1","z":"2","hex":"#5c5050","rgb":[92,80,80],"name":"Gravel","mat_id":"28","file":"textures\/13_0.png","transparent":false,"opacity":1,"texture":"13_0.png"},"1":{"x":14,"y":"1","z":"1","hex":"#11b029","rgb":[17,176,41],"name":"Grass","mat_id":"14","file":"","transparent":false,"opacity":1,"texture":"2_0.png"}},"5":{"1":{"x":5,"y":"1","z":"1","hex":"#11b029","rgb":[17,176,41],"name":"Grass","mat_id":"14","file":"","transparent":false,"opacity":1,"texture":"2_0.png"},"5":{"x":5,"y":"1","z":"5","hex":"#11b029","rgb":[17,176,41],"name":"Grass","mat_id":"14","file":"","transparent":false,"opacity":1,"texture":"2_0.png"},"4":{"x":5,"y":"1","z":"4","hex":"#78543f","rgb":[120,84,63],"name":"Dirt","mat_id":"15","file":"textures\/3_0.png","transparent":false,"opacity":1,"texture":"3_0.png"},"3":{"x":5,"y":"1","z":"3","hex":"#11b029","rgb":[17,176,41],"name":"Grass","mat_id":"14","file":"","transparent":false,"opacity":1,"texture":"2_0.png"},"2":{"x":5,"y":"1","z":"2","hex":"#78543f","rgb":[120,84,63],"name":"Dirt","mat_id":"15","file":"textures\/3_0.png","transparent":false,"opacity":1,"texture":"3_0.png"}},"13":{"1":{"x":13,"y":"1","z":"1","hex":"#11b029","rgb":[17,176,41],"name":"Grass","mat_id":"14","file":"","transparent":false,"opacity":1,"texture":"2_0.png"},"2":{"x":13,"y":"1","z":"2","hex":"#11b029","rgb":[17,176,41],"name":"Grass","mat_id":"14","file":"","transparent":false,"opacity":1,"texture":"2_0.png"},"3":{"x":13,"y":"1","z":"3","hex":"#78543f","rgb":[120,84,63],"name":"Dirt","mat_id":"15","file":"textures\/3_0.png","transparent":false,"opacity":1,"texture":"3_0.png"},"4":{"x":13,"y":"1","z":"4","hex":"#11b029","rgb":[17,176,41],"name":"Grass","mat_id":"14","file":"","transparent":false,"opacity":1,"texture":"2_0.png"},"5":{"x":13,"y":"1","z":"5","hex":"#7a3d3d","rgb":[122,61,61],"name":"Coarse Dirt","mat_id":"16","file":"textures\/3_1.png","transparent":false,"opacity":1,"texture":"3_1.png"}},"12":{"1":{"x":12,"y":"1","z":"1","hex":"#5c5050","rgb":[92,80,80],"name":"Gravel","mat_id":"28","file":"textures\/13_0.png","transparent":false,"opacity":1,"texture":"13_0.png"},"2":{"x":12,"y":"1","z":"2","hex":"#7a3d3d","rgb":[122,61,61],"name":"Coarse Dirt","mat_id":"16","file":"textures\/3_1.png","transparent":false,"opacity":1,"texture":"3_1.png"},"3":{"x":12,"y":"1","z":"3","hex":"#78543f","rgb":[120,84,63],"name":"Dirt","mat_id":"15","file":"textures\/3_0.png","transparent":false,"opacity":1,"texture":"3_0.png"},"4":{"x":12,"y":"1","z":"4","hex":"#11b029","rgb":[17,176,41],"name":"Grass","mat_id":"14","file":"","transparent":false,"opacity":1,"texture":"2_0.png"},"5":{"x":12,"y":"1","z":"5","hex":"#11b029","rgb":[17,176,41],"name":"Grass","mat_id":"14","file":"","transparent":false,"opacity":1,"texture":"2_0.png"}},"15":{"1":{"x":15,"y":"1","z":"1","hex":"#7a3d3d","rgb":[122,61,61],"name":"Coarse Dirt","mat_id":"16","file":"textures\/3_1.png","transparent":false,"opacity":1,"texture":"3_1.png"},"2":{"x":15,"y":"1","z":"2","hex":"#11b029","rgb":[17,176,41],"name":"Grass","mat_id":"14","file":"","transparent":false,"opacity":1,"texture":"2_0.png"},"3":{"x":15,"y":"1","z":"3","hex":"#78543f","rgb":[120,84,63],"name":"Dirt","mat_id":"15","file":"textures\/3_0.png","transparent":false,"opacity":1,"texture":"3_0.png"},"4":{"x":15,"y":"1","z":"4","hex":"#11b029","rgb":[17,176,41],"name":"Grass","mat_id":"14","file":"","transparent":false,"opacity":1,"texture":"2_0.png"},"5":{"x":15,"y":"1","z":"5","hex":"#11b029","rgb":[17,176,41],"name":"Grass","mat_id":"14","file":"","transparent":false,"opacity":1,"texture":"2_0.png"}},"6":{"5":{"x":6,"y":"1","z":"5","hex":"#5c5050","rgb":[92,80,80],"name":"Gravel","mat_id":"28","file":"textures\/13_0.png","transparent":false,"opacity":1,"texture":"13_0.png"},"4":{"x":6,"y":"1","z":"4","hex":"#78543f","rgb":[120,84,63],"name":"Dirt","mat_id":"15","file":"textures\/3_0.png","transparent":false,"opacity":1,"texture":"3_0.png"},"3":{"x":6,"y":"1","z":"3","hex":"#78543f","rgb":[120,84,63],"name":"Dirt","mat_id":"15","file":"textures\/3_0.png","transparent":false,"opacity":1,"texture":"3_0.png"},"2":{"x":6,"y":"1","z":"2","hex":"#78543f","rgb":[120,84,63],"name":"Dirt","mat_id":"15","file":"textures\/3_0.png","transparent":false,"opacity":1,"texture":"3_0.png"},"1":{"x":6,"y":"1","z":"1","hex":"#5c5050","rgb":[92,80,80],"name":"Gravel","mat_id":"28","file":"textures\/13_0.png","transparent":false,"opacity":1,"texture":"13_0.png"}},"9":{"1":{"x":9,"y":"1","z":"1","hex":"#5c5050","rgb":[92,80,80],"name":"Gravel","mat_id":"28","file":"textures\/13_0.png","transparent":false,"opacity":1,"texture":"13_0.png"},"2":{"x":9,"y":"1","z":"2","hex":"#11b029","rgb":[17,176,41],"name":"Grass","mat_id":"14","file":"","transparent":false,"opacity":1,"texture":"2_0.png"},"3":{"x":9,"y":"1","z":"3","hex":"#78543f","rgb":[120,84,63],"name":"Dirt","mat_id":"15","file":"textures\/3_0.png","transparent":false,"opacity":1,"texture":"3_0.png"},"4":{"x":9,"y":"1","z":"4","hex":"#11b029","rgb":[17,176,41],"name":"Grass","mat_id":"14","file":"","transparent":false,"opacity":1,"texture":"2_0.png"},"5":{"x":9,"y":"1","z":"5","hex":"#7a3d3d","rgb":[122,61,61],"name":"Coarse Dirt","mat_id":"16","file":"textures\/3_1.png","transparent":false,"opacity":1,"texture":"3_1.png"}},"7":{"5":{"x":7,"y":"1","z":"5","hex":"#5c5050","rgb":[92,80,80],"name":"Gravel","mat_id":"28","file":"textures\/13_0.png","transparent":false,"opacity":1,"texture":"13_0.png"},"4":{"x":7,"y":"1","z":"4","hex":"#11b029","rgb":[17,176,41],"name":"Grass","mat_id":"14","file":"","transparent":false,"opacity":1,"texture":"2_0.png"},"3":{"x":7,"y":"1","z":"3","hex":"#78543f","rgb":[120,84,63],"name":"Dirt","mat_id":"15","file":"textures\/3_0.png","transparent":false,"opacity":1,"texture":"3_0.png"},"2":{"x":7,"y":"1","z":"2","hex":"#11b029","rgb":[17,176,41],"name":"Grass","mat_id":"14","file":"","transparent":false,"opacity":1,"texture":"2_0.png"},"1":{"x":7,"y":"1","z":"1","hex":"#7a3d3d","rgb":[122,61,61],"name":"Coarse Dirt","mat_id":"16","file":"textures\/3_1.png","transparent":false,"opacity":1,"texture":"3_1.png"}},"8":{"1":{"x":8,"y":"1","z":"1","hex":"#11b029","rgb":[17,176,41],"name":"Grass","mat_id":"14","file":"","transparent":false,"opacity":1,"texture":"2_0.png"},"2":{"x":8,"y":"1","z":"2","hex":"#7a3d3d","rgb":[122,61,61],"name":"Coarse Dirt","mat_id":"16","file":"textures\/3_1.png","transparent":false,"opacity":1,"texture":"3_1.png"},"3":{"x":8,"y":"1","z":"3","hex":"#78543f","rgb":[120,84,63],"name":"Dirt","mat_id":"15","file":"textures\/3_0.png","transparent":false,"opacity":1,"texture":"3_0.png"},"4":{"x":8,"y":"1","z":"4","hex":"#7a3d3d","rgb":[122,61,61],"name":"Coarse Dirt","mat_id":"16","file":"textures\/3_1.png","transparent":false,"opacity":1,"texture":"3_1.png"},"5":{"x":8,"y":"1","z":"5","hex":"#11b029","rgb":[17,176,41],"name":"Grass","mat_id":"14","file":"","transparent":false,"opacity":1,"texture":"2_0.png"}},"10":{"5":{"x":10,"y":"1","z":"5","hex":"#11b029","rgb":[17,176,41],"name":"Grass","mat_id":"14","file":"","transparent":false,"opacity":1,"texture":"2_0.png"},"1":{"x":10,"y":"1","z":"1","hex":"#11b029","rgb":[17,176,41],"name":"Grass","mat_id":"14","file":"","transparent":false,"opacity":1,"texture":"2_0.png"},"2":{"x":10,"y":"1","z":"2","hex":"#11b029","rgb":[17,176,41],"name":"Grass","mat_id":"14","file":"","transparent":false,"opacity":1,"texture":"2_0.png"},"3":{"x":10,"y":"1","z":"3","hex":"#78543f","rgb":[120,84,63],"name":"Dirt","mat_id":"15","file":"textures\/3_0.png","transparent":false,"opacity":1,"texture":"3_0.png"},"4":{"x":10,"y":"1","z":"4","hex":"#5c5050","rgb":[92,80,80],"name":"Gravel","mat_id":"28","file":"textures\/13_0.png","transparent":false,"opacity":1,"texture":"13_0.png"}},"11":{"1":{"x":11,"y":"1","z":"1","hex":"#5c5050","rgb":[92,80,80],"name":"Gravel","mat_id":"28","file":"textures\/13_0.png","transparent":false,"opacity":1,"texture":"13_0.png"},"2":{"x":11,"y":"1","z":"2","hex":"#11b029","rgb":[17,176,41],"name":"Grass","mat_id":"14","file":"","transparent":false,"opacity":1,"texture":"2_0.png"},"3":{"x":11,"y":"1","z":"3","hex":"#78543f","rgb":[120,84,63],"name":"Dirt","mat_id":"15","file":"textures\/3_0.png","transparent":false,"opacity":1,"texture":"3_0.png"},"4":{"x":11,"y":"1","z":"4","hex":"#11b029","rgb":[17,176,41],"name":"Grass","mat_id":"14","file":"","transparent":false,"opacity":1,"texture":"2_0.png"},"5":{"x":11,"y":"1","z":"5","hex":"#5c5050","rgb":[92,80,80],"name":"Gravel","mat_id":"28","file":"textures\/13_0.png","transparent":false,"opacity":1,"texture":"13_0.png"}},"2":{"1":{"x":2,"y":"1","z":"1","hex":"#11b029","rgb":[17,176,41],"name":"Grass","mat_id":"14","file":"","transparent":false,"opacity":1,"texture":"2_0.png"},"5":{"x":2,"y":"1","z":"5","hex":"#11b029","rgb":[17,176,41],"name":"Grass","mat_id":"14","file":"","transparent":false,"opacity":1,"texture":"2_0.png"},"2":{"x":2,"y":"1","z":"2","hex":"#11b029","rgb":[17,176,41],"name":"Grass","mat_id":"14","file":"","transparent":false,"opacity":1,"texture":"2_0.png"},"3":{"x":2,"y":"1","z":"3","hex":"#11b029","rgb":[17,176,41],"name":"Grass","mat_id":"14","file":"","transparent":false,"opacity":1,"texture":"2_0.png"},"4":{"x":2,"y":"1","z":"4","hex":"#11b029","rgb":[17,176,41],"name":"Grass","mat_id":"14","file":"","transparent":false,"opacity":1,"texture":"2_0.png"}},"3":{"5":{"x":3,"y":"1","z":"5","hex":"#7a3d3d","rgb":[122,61,61],"name":"Coarse Dirt","mat_id":"16","file":"textures\/3_1.png","transparent":false,"opacity":1,"texture":"3_1.png"},"4":{"x":3,"y":"1","z":"4","hex":"#11b029","rgb":[17,176,41],"name":"Grass","mat_id":"14","file":"","transparent":false,"opacity":1,"texture":"2_0.png"},"3":{"x":3,"y":"1","z":"3","hex":"#11b029","rgb":[17,176,41],"name":"Grass","mat_id":"14","file":"","transparent":false,"opacity":1,"texture":"2_0.png"},"2":{"x":3,"y":"1","z":"2","hex":"#7a3d3d","rgb":[122,61,61],"name":"Coarse Dirt","mat_id":"16","file":"textures\/3_1.png","transparent":false,"opacity":1,"texture":"3_1.png"},"1":{"x":3,"y":"1","z":"1","hex":"#11b029","rgb":[17,176,41],"name":"Grass","mat_id":"14","file":"","transparent":false,"opacity":1,"texture":"2_0.png"}},"18":{"5":{"x":18,"y":"1","z":"5","hex":"#5c5050","rgb":[92,80,80],"name":"Gravel","mat_id":"28","file":"textures\/13_0.png","transparent":false,"opacity":1,"texture":"13_0.png"},"4":{"x":18,"y":"1","z":"4","hex":"#78543f","rgb":[120,84,63],"name":"Dirt","mat_id":"15","file":"textures\/3_0.png","transparent":false,"opacity":1,"texture":"3_0.png"},"3":{"x":18,"y":"1","z":"3","hex":"#78543f","rgb":[120,84,63],"name":"Dirt","mat_id":"15","file":"textures\/3_0.png","transparent":false,"opacity":1,"texture":"3_0.png"},"2":{"x":18,"y":"1","z":"2","hex":"#78543f","rgb":[120,84,63],"name":"Dirt","mat_id":"15","file":"textures\/3_0.png","transparent":false,"opacity":1,"texture":"3_0.png"},"1":{"x":18,"y":"1","z":"1","hex":"#7a3d3d","rgb":[122,61,61],"name":"Coarse Dirt","mat_id":"16","file":"textures\/3_1.png","transparent":false,"opacity":1,"texture":"3_1.png"}},"1":{"4":{"x":1,"y":"1","z":"4","hex":"#11b029","rgb":[17,176,41],"name":"Grass","mat_id":"14","file":"","transparent":false,"opacity":1,"texture":"2_0.png"},"3":{"x":1,"y":"1","z":"3","hex":"#11b029","rgb":[17,176,41],"name":"Grass","mat_id":"14","file":"","transparent":false,"opacity":1,"texture":"2_0.png"},"1":{"x":1,"y":"1","z":"1","hex":"#11b029","rgb":[17,176,41],"name":"Grass","mat_id":"14","file":"","transparent":false,"opacity":1,"texture":"2_0.png"},"2":{"x":1,"y":"1","z":"2","hex":"#11b029","rgb":[17,176,41],"name":"Grass","mat_id":"14","file":"","transparent":false,"opacity":1,"texture":"2_0.png"},"5":{"x":1,"y":"1","z":"5","hex":"#11b029","rgb":[17,176,41],"name":"Grass","mat_id":"14","file":"","transparent":false,"opacity":1,"texture":"2_0.png"}},"17":{"1":{"x":17,"y":"1","z":"1","hex":"#11b029","rgb":[17,176,41],"name":"Grass","mat_id":"14","file":"","transparent":false,"opacity":1,"texture":"2_0.png"},"2":{"x":17,"y":"1","z":"2","hex":"#b88830","rgb":[184,136,48],"name":"Oak Wood Plank","mat_id":"19","file":"textures\/5_0.png","transparent":false,"opacity":1,"texture":"5_0.png"},"4":{"x":17,"y":"1","z":"4","hex":"#78543f","rgb":[120,84,63],"name":"Dirt","mat_id":"15","file":"textures\/3_0.png","transparent":false,"opacity":1,"texture":"3_0.png"},"5":{"x":17,"y":"1","z":"5","hex":"#11b029","rgb":[17,176,41],"name":"Grass","mat_id":"14","file":"","transparent":false,"opacity":1,"texture":"2_0.png"},"3":{"x":17,"y":"1","z":"3","hex":"#11b029","rgb":[17,176,41],"name":"Grass","mat_id":"14","file":"","transparent":false,"opacity":1,"texture":"2_0.png"}},"19":{"2":{"x":19,"y":"1","z":"2","hex":"#5c5050","rgb":[92,80,80],"name":"Gravel","mat_id":"28","file":"textures\/13_0.png","transparent":false,"opacity":1,"texture":"13_0.png"},"4":{"x":19,"y":"1","z":"4","hex":"#5c5050","rgb":[92,80,80],"name":"Gravel","mat_id":"28","file":"textures\/13_0.png","transparent":false,"opacity":1,"texture":"13_0.png"},"3":{"x":19,"y":"1","z":"3","hex":"#11b029","rgb":[17,176,41],"name":"Grass","mat_id":"14","file":"","transparent":false,"opacity":1,"texture":"2_0.png"},"5":{"x":19,"y":"1","z":"5","hex":"#11b029","rgb":[17,176,41],"name":"Grass","mat_id":"14","file":"","transparent":false,"opacity":1,"texture":"2_0.png"},"1":{"x":19,"y":"1","z":"1","hex":"#11b029","rgb":[17,176,41],"name":"Grass","mat_id":"14","file":"","transparent":false,"opacity":1,"texture":"2_0.png"}},"16":{"4":{"x":16,"y":"1","z":"4","hex":"#78543f","rgb":[120,84,63],"name":"Dirt","mat_id":"15","file":"textures\/3_0.png","transparent":false,"opacity":1,"texture":"3_0.png"},"3":{"x":16,"y":"1","z":"3","hex":"#78543f","rgb":[120,84,63],"name":"Dirt","mat_id":"15","file":"textures\/3_0.png","transparent":false,"opacity":1,"texture":"3_0.png"},"2":{"x":16,"y":"1","z":"2","hex":"#78543f","rgb":[120,84,63],"name":"Dirt","mat_id":"15","file":"textures\/3_0.png","transparent":false,"opacity":1,"texture":"3_0.png"},"1":{"x":16,"y":"1","z":"1","hex":"#11b029","rgb":[17,176,41],"name":"Grass","mat_id":"14","file":"","transparent":false,"opacity":1,"texture":"2_0.png"},"5":{"x":16,"y":"1","z":"5","hex":"#7a3d3d","rgb":[122,61,61],"name":"Coarse Dirt","mat_id":"16","file":"textures\/3_1.png","transparent":false,"opacity":1,"texture":"3_1.png"}}},"2":{"11":{"3":{"x":11,"y":"2","z":"3","hex":"#b88830","rgb":[184,136,48],"name":"Oak Wood Plank","mat_id":"19","file":"textures\/5_0.png","transparent":false,"opacity":1,"texture":"5_0.png"},"4":{"x":11,"y":"2","z":"4","hex":"#8b6b4e","rgb":[139,107,78],"name":"Oak Wood Stairs (West, Normal)","mat_id":"297","file":"","transparent":false,"opacity":1,"texture":"53_1.png"},"2":{"x":11,"y":"2","z":"2","hex":"#8b6b4e","rgb":[139,107,78],"name":"Oak Wood Stairs (East, Normal)","mat_id":"101","file":"","transparent":false,"opacity":1,"texture":"53_0.png"}},"9":{"2":{"x":9,"y":"2","z":"2","hex":"#8b6b4e","rgb":[139,107,78],"name":"Oak Wood Stairs (East, Normal)","mat_id":"101","file":"","transparent":false,"opacity":1,"texture":"53_0.png"},"3":{"x":9,"y":"2","z":"3","hex":"#b88830","rgb":[184,136,48],"name":"Oak Wood Plank","mat_id":"19","file":"textures\/5_0.png","transparent":false,"opacity":1,"texture":"5_0.png"},"4":{"x":9,"y":"2","z":"4","hex":"#8b6b4e","rgb":[139,107,78],"name":"Oak Wood Stairs (West, Normal)","mat_id":"297","file":"","transparent":false,"opacity":1,"texture":"53_1.png"}},"17":{"5":{"x":17,"y":"2","z":"5","hex":"#8b6b4e","rgb":[139,107,78],"name":"Oak Wood Stairs (West, Normal)","mat_id":"297","file":"","transparent":false,"opacity":1,"texture":"53_1.png"},"1":{"x":17,"y":"2","z":"1","hex":"#8b6b4e","rgb":[139,107,78],"name":"Oak Wood Stairs (East, Normal)","mat_id":"101","file":"","transparent":false,"opacity":1,"texture":"53_0.png"},"2":{"x":17,"y":"2","z":"2","hex":"#b88830","rgb":[184,136,48],"name":"Oak Wood Plank","mat_id":"19","file":"textures\/5_0.png","transparent":false,"opacity":1,"texture":"5_0.png"},"4":{"x":17,"y":"2","z":"4","hex":"#b88830","rgb":[184,136,48],"name":"Oak Wood Plank","mat_id":"19","file":"textures\/5_0.png","transparent":false,"opacity":1,"texture":"5_0.png"}},"8":{"2":{"x":8,"y":"2","z":"2","hex":"#25100b","rgb":[37,16,11],"name":"Dark Oak Fence","mat_id":"910","file":"","transparent":false,"opacity":1,"texture":"191_0.png"},"3":{"x":8,"y":"2","z":"3","hex":"#b88830","rgb":[184,136,48],"name":"Oak Wood Plank","mat_id":"19","file":"textures\/5_0.png","transparent":false,"opacity":1,"texture":"5_0.png"},"4":{"x":8,"y":"2","z":"4","hex":"#25100b","rgb":[37,16,11],"name":"Dark Oak Fence","mat_id":"910","file":"","transparent":false,"opacity":1,"texture":"191_0.png"}},"7":{"2":{"x":7,"y":"2","z":"2","hex":"#8b6b4e","rgb":[139,107,78],"name":"Oak Wood Stairs (East, Normal)","mat_id":"101","file":"","transparent":false,"opacity":1,"texture":"53_0.png"},"3":{"x":7,"y":"2","z":"3","hex":"#b88830","rgb":[184,136,48],"name":"Oak Wood Plank","mat_id":"19","file":"textures\/5_0.png","transparent":false,"opacity":1,"texture":"5_0.png"},"4":{"x":7,"y":"2","z":"4","hex":"#8b6b4e","rgb":[139,107,78],"name":"Oak Wood Stairs (West, Normal)","mat_id":"297","file":"","transparent":false,"opacity":1,"texture":"53_1.png"}},"19":{"2":{"x":19,"y":"2","z":"2","hex":"#49371f","rgb":[73,55,31],"name":"Spruce Fence","mat_id":"907","file":"","transparent":false,"opacity":1,"texture":"188_0.png"},"3":{"x":19,"y":"2","z":"3","hex":"#8b6b4e","rgb":[139,107,78],"name":"Oak Wood Stairs (South, Normal)","mat_id":"298","file":"","transparent":false,"opacity":1,"texture":"53_2.png"},"4":{"x":19,"y":"2","z":"4","hex":"#25100b","rgb":[37,16,11],"name":"Dark Oak Fence","mat_id":"910","file":"","transparent":false,"opacity":1,"texture":"191_0.png"}},"18":{"1":{"x":18,"y":"2","z":"1","hex":"#25100b","rgb":[37,16,11],"name":"Dark Oak Fence","mat_id":"910","file":"","transparent":false,"opacity":1,"texture":"191_0.png"},"2":{"x":18,"y":"2","z":"2","hex":"#634830","rgb":[99,72,48],"name":"Spruce Wood","mat_id":"30","file":"","transparent":false,"opacity":1,"texture":"17_1.png"},"3":{"x":18,"y":"2","z":"3","hex":"#b88830","rgb":[184,136,48],"name":"Oak Wood Plank","mat_id":"19","file":"textures\/5_0.png","transparent":false,"opacity":1,"texture":"5_0.png"},"4":{"x":18,"y":"2","z":"4","hex":"#634830","rgb":[99,72,48],"name":"Spruce Wood","mat_id":"30","file":"","transparent":false,"opacity":1,"texture":"17_1.png"},"5":{"x":18,"y":"2","z":"5","hex":"#25100b","rgb":[37,16,11],"name":"Dark Oak Fence","mat_id":"910","file":"","transparent":false,"opacity":1,"texture":"191_0.png"}},"10":{"4":{"x":10,"y":"2","z":"4","hex":"#49371f","rgb":[73,55,31],"name":"Spruce Fence","mat_id":"907","file":"","transparent":false,"opacity":1,"texture":"188_0.png"},"3":{"x":10,"y":"2","z":"3","hex":"#b88830","rgb":[184,136,48],"name":"Oak Wood Plank","mat_id":"19","file":"textures\/5_0.png","transparent":false,"opacity":1,"texture":"5_0.png"},"2":{"x":10,"y":"2","z":"2","hex":"#49371f","rgb":[73,55,31],"name":"Spruce Fence","mat_id":"907","file":"","transparent":false,"opacity":1,"texture":"188_0.png"},"1":{"x":10,"y":"2","z":"1","hex":"#2f8948","rgb":[47,137,72],"name":"Spruce Leaves (No Decay)","mat_id":"329","file":"","transparent":false,"opacity":1,"texture":"18_5.png"}},"3":{"4":{"x":3,"y":"2","z":"4","hex":"#25100b","rgb":[37,16,11],"name":"Dark Oak Fence","mat_id":"910","file":"","transparent":false,"opacity":1,"texture":"191_0.png"},"2":{"x":3,"y":"2","z":"2","hex":"#25100b","rgb":[37,16,11],"name":"Dark Oak Fence","mat_id":"910","file":"","transparent":false,"opacity":1,"texture":"191_0.png"},"3":{"x":3,"y":"2","z":"3","hex":"#8b6b4e","rgb":[139,107,78],"name":"Oak Wood Stairs (North, Normal)","mat_id":"296","file":"","transparent":false,"opacity":1,"texture":"53_3.png"}},"4":{"2":{"x":4,"y":"2","z":"2","hex":"#634830","rgb":[99,72,48],"name":"Spruce Wood","mat_id":"30","file":"","transparent":false,"opacity":1,"texture":"17_1.png"},"4":{"x":4,"y":"2","z":"4","hex":"#634830","rgb":[99,72,48],"name":"Spruce Wood","mat_id":"30","file":"","transparent":false,"opacity":1,"texture":"17_1.png"},"5":{"x":4,"y":"2","z":"5","hex":"#49371f","rgb":[73,55,31],"name":"Spruce Fence","mat_id":"907","file":"","transparent":false,"opacity":1,"texture":"188_0.png"},"1":{"x":4,"y":"2","z":"1","hex":"#49371f","rgb":[73,55,31],"name":"Spruce Fence","mat_id":"907","file":"","transparent":false,"opacity":1,"texture":"188_0.png"},"3":{"x":4,"y":"2","z":"3","hex":"#b88830","rgb":[184,136,48],"name":"Oak Wood Plank","mat_id":"19","file":"textures\/5_0.png","transparent":false,"opacity":1,"texture":"5_0.png"}},"15":{"4":{"x":15,"y":"2","z":"4","hex":"#8b6b4e","rgb":[139,107,78],"name":"Oak Wood Stairs (West, Normal)","mat_id":"297","file":"","transparent":false,"opacity":1,"texture":"53_1.png"},"5":{"x":15,"y":"2","z":"5","hex":"#2f8948","rgb":[47,137,72],"name":"Spruce Leaves (No Decay)","mat_id":"329","file":"","transparent":false,"opacity":1,"texture":"18_5.png"},"3":{"x":15,"y":"2","z":"3","hex":"#b88830","rgb":[184,136,48],"name":"Oak Wood Plank","mat_id":"19","file":"textures\/5_0.png","transparent":false,"opacity":1,"texture":"5_0.png"},"2":{"x":15,"y":"2","z":"2","hex":"#8b6b4e","rgb":[139,107,78],"name":"Oak Wood Stairs (East, Normal)","mat_id":"101","file":"","transparent":false,"opacity":1,"texture":"53_0.png"}},"5":{"1":{"x":5,"y":"2","z":"1","hex":"#8b6b4e","rgb":[139,107,78],"name":"Oak Wood Stairs (East, Normal)","mat_id":"101","file":"","transparent":false,"opacity":1,"texture":"53_0.png"},"2":{"x":5,"y":"2","z":"2","hex":"#b88830","rgb":[184,136,48],"name":"Oak Wood Plank","mat_id":"19","file":"textures\/5_0.png","transparent":false,"opacity":1,"texture":"5_0.png"},"5":{"x":5,"y":"2","z":"5","hex":"#8b6b4e","rgb":[139,107,78],"name":"Oak Wood Stairs (West, Normal)","mat_id":"297","file":"","transparent":false,"opacity":1,"texture":"53_1.png"},"4":{"x":5,"y":"2","z":"4","hex":"#b88830","rgb":[184,136,48],"name":"Oak Wood Plank","mat_id":"19","file":"textures\/5_0.png","transparent":false,"opacity":1,"texture":"5_0.png"}},"14":{"2":{"x":14,"y":"2","z":"2","hex":"#49371f","rgb":[73,55,31],"name":"Spruce Fence","mat_id":"907","file":"","transparent":false,"opacity":1,"texture":"188_0.png"},"3":{"x":14,"y":"2","z":"3","hex":"#b88830","rgb":[184,136,48],"name":"Oak Wood Plank","mat_id":"19","file":"textures\/5_0.png","transparent":false,"opacity":1,"texture":"5_0.png"},"4":{"x":14,"y":"2","z":"4","hex":"#25100b","rgb":[37,16,11],"name":"Dark Oak Fence","mat_id":"910","file":"","transparent":false,"opacity":1,"texture":"191_0.png"}},"16":{"5":{"x":16,"y":"2","z":"5","hex":"#49371f","rgb":[73,55,31],"name":"Spruce Fence","mat_id":"907","file":"","transparent":false,"opacity":1,"texture":"188_0.png"},"4":{"x":16,"y":"2","z":"4","hex":"#634830","rgb":[99,72,48],"name":"Spruce Wood","mat_id":"30","file":"","transparent":false,"opacity":1,"texture":"17_1.png"},"3":{"x":16,"y":"2","z":"3","hex":"#b88830","rgb":[184,136,48],"name":"Oak Wood Plank","mat_id":"19","file":"textures\/5_0.png","transparent":false,"opacity":1,"texture":"5_0.png"},"2":{"x":16,"y":"2","z":"2","hex":"#634830","rgb":[99,72,48],"name":"Spruce Wood","mat_id":"30","file":"","transparent":false,"opacity":1,"texture":"17_1.png"},"1":{"x":16,"y":"2","z":"1","hex":"#25100b","rgb":[37,16,11],"name":"Dark Oak Fence","mat_id":"910","file":"","transparent":false,"opacity":1,"texture":"191_0.png"}},"6":{"1":{"x":6,"y":"2","z":"1","hex":"#25100b","rgb":[37,16,11],"name":"Dark Oak Fence","mat_id":"910","file":"","transparent":false,"opacity":1,"texture":"191_0.png"},"5":{"x":6,"y":"2","z":"5","hex":"#25100b","rgb":[37,16,11],"name":"Dark Oak Fence","mat_id":"910","file":"","transparent":false,"opacity":1,"texture":"191_0.png"},"4":{"x":6,"y":"2","z":"4","hex":"#634830","rgb":[99,72,48],"name":"Spruce Wood","mat_id":"30","file":"","transparent":false,"opacity":1,"texture":"17_1.png"},"3":{"x":6,"y":"2","z":"3","hex":"#b88830","rgb":[184,136,48],"name":"Oak Wood Plank","mat_id":"19","file":"textures\/5_0.png","transparent":false,"opacity":1,"texture":"5_0.png"},"2":{"x":6,"y":"2","z":"2","hex":"#634830","rgb":[99,72,48],"name":"Spruce Wood","mat_id":"30","file":"","transparent":false,"opacity":1,"texture":"17_1.png"}},"13":{"3":{"x":13,"y":"2","z":"3","hex":"#b88830","rgb":[184,136,48],"name":"Oak Wood Plank","mat_id":"19","file":"textures\/5_0.png","transparent":false,"opacity":1,"texture":"5_0.png"},"4":{"x":13,"y":"2","z":"4","hex":"#8b6b4e","rgb":[139,107,78],"name":"Oak Wood Stairs (West, Normal)","mat_id":"297","file":"","transparent":false,"opacity":1,"texture":"53_1.png"},"2":{"x":13,"y":"2","z":"2","hex":"#8b6b4e","rgb":[139,107,78],"name":"Oak Wood Stairs (East, Normal)","mat_id":"101","file":"","transparent":false,"opacity":1,"texture":"53_0.png"}},"12":{"2":{"x":12,"y":"2","z":"2","hex":"#25100b","rgb":[37,16,11],"name":"Dark Oak Fence","mat_id":"910","file":"","transparent":false,"opacity":1,"texture":"191_0.png"},"3":{"x":12,"y":"2","z":"3","hex":"#b88830","rgb":[184,136,48],"name":"Oak Wood Plank","mat_id":"19","file":"textures\/5_0.png","transparent":false,"opacity":1,"texture":"5_0.png"},"4":{"x":12,"y":"2","z":"4","hex":"#25100b","rgb":[37,16,11],"name":"Dark Oak Fence","mat_id":"910","file":"","transparent":false,"opacity":1,"texture":"191_0.png"}}},"3":{"7":{"3":{"x":7,"y":"3","z":"3","hex":"#b88830","rgb":[184,136,48],"name":"Oak Wood Plank","mat_id":"19","file":"textures\/5_0.png","transparent":false,"opacity":1,"texture":"5_0.png"},"2":{"x":7,"y":"3","z":"2","hex":"#2f8948","rgb":[47,137,72],"name":"Spruce Leaves (No Decay)","mat_id":"329","file":"","transparent":false,"opacity":1,"texture":"18_5.png"}},"3":{"3":{"x":3,"y":"3","z":"3","hex":"#c9b62c","rgb":[201,182,44],"name":"Torch (Facing South)","mat_id":"448","file":"","transparent":false,"opacity":1,"texture":"50_3.png"}},"4":{"4":{"x":4,"y":"3","z":"4","hex":"#634830","rgb":[99,72,48],"name":"Spruce Wood","mat_id":"30","file":"","transparent":false,"opacity":1,"texture":"17_1.png"},"3":{"x":4,"y":"3","z":"3","hex":"#b88830","rgb":[184,136,48],"name":"Oak Wood Plank","mat_id":"19","file":"textures\/5_0.png","transparent":false,"opacity":1,"texture":"5_0.png"},"2":{"x":4,"y":"3","z":"2","hex":"#634830","rgb":[99,72,48],"name":"Spruce Wood","mat_id":"30","file":"","transparent":false,"opacity":1,"texture":"17_1.png"}},"6":{"3":{"x":6,"y":"3","z":"3","hex":"#b88830","rgb":[184,136,48],"name":"Oak Wood Plank","mat_id":"19","file":"textures\/5_0.png","transparent":false,"opacity":1,"texture":"5_0.png"},"2":{"x":6,"y":"3","z":"2","hex":"#634830","rgb":[99,72,48],"name":"Spruce Wood","mat_id":"30","file":"","transparent":false,"opacity":1,"texture":"17_1.png"},"4":{"x":6,"y":"3","z":"4","hex":"#634830","rgb":[99,72,48],"name":"Spruce Wood","mat_id":"30","file":"","transparent":false,"opacity":1,"texture":"17_1.png"}},"5":{"4":{"x":5,"y":"3","z":"4","hex":"#b88830","rgb":[184,136,48],"name":"Oak Wood Plank","mat_id":"19","file":"textures\/5_0.png","transparent":false,"opacity":1,"texture":"5_0.png"},"2":{"x":5,"y":"3","z":"2","hex":"#b88830","rgb":[184,136,48],"name":"Oak Wood Plank","mat_id":"19","file":"textures\/5_0.png","transparent":false,"opacity":1,"texture":"5_0.png"}},"19":{"3":{"x":19,"y":"3","z":"3","hex":"#c9b62c","rgb":[201,182,44],"name":"Torch (Facing North)","mat_id":"449","file":"","transparent":false,"opacity":1,"texture":"50_4.png"}},"16":{"4":{"x":16,"y":"3","z":"4","hex":"#634830","rgb":[99,72,48],"name":"Spruce Wood","mat_id":"30","file":"","transparent":false,"opacity":1,"texture":"17_1.png"},"3":{"x":16,"y":"3","z":"3","hex":"#b88830","rgb":[184,136,48],"name":"Oak Wood Plank","mat_id":"19","file":"textures\/5_0.png","transparent":false,"opacity":1,"texture":"5_0.png"},"2":{"x":16,"y":"3","z":"2","hex":"#634830","rgb":[99,72,48],"name":"Spruce Wood","mat_id":"30","file":"","transparent":false,"opacity":1,"texture":"17_1.png"}},"12":{"3":{"x":12,"y":"3","z":"3","hex":"#b88830","rgb":[184,136,48],"name":"Oak Wood Plank","mat_id":"19","file":"textures\/5_0.png","transparent":false,"opacity":1,"texture":"5_0.png"}},"11":{"3":{"x":11,"y":"3","z":"3","hex":"#8b6b4e","rgb":[139,107,78],"name":"Oak Wood Stairs (East, Normal)","mat_id":"101","file":"","transparent":false,"opacity":1,"texture":"53_0.png"}},"15":{"2":{"x":15,"y":"3","z":"2","hex":"#2f8948","rgb":[47,137,72],"name":"Spruce Leaves (No Decay)","mat_id":"329","file":"","transparent":false,"opacity":1,"texture":"18_5.png"},"3":{"x":15,"y":"3","z":"3","hex":"#b88830","rgb":[184,136,48],"name":"Oak Wood Plank","mat_id":"19","file":"textures\/5_0.png","transparent":false,"opacity":1,"texture":"5_0.png"}},"17":{"4":{"x":17,"y":"3","z":"4","hex":"#b88830","rgb":[184,136,48],"name":"Oak Wood Plank","mat_id":"19","file":"textures\/5_0.png","transparent":false,"opacity":1,"texture":"5_0.png"},"2":{"x":17,"y":"3","z":"2","hex":"#b88830","rgb":[184,136,48],"name":"Oak Wood Plank","mat_id":"19","file":"textures\/5_0.png","transparent":false,"opacity":1,"texture":"5_0.png"}},"8":{"3":{"x":8,"y":"3","z":"3","hex":"#8b6b4e","rgb":[139,107,78],"name":"Oak Wood Stairs (West, Normal)","mat_id":"297","file":"","transparent":false,"opacity":1,"texture":"53_1.png"}},"10":{"3":{"x":10,"y":"3","z":"3","hex":"#8b6b4e","rgb":[139,107,78],"name":"Oak Wood Stairs (West, Upside-down)","mat_id":"407","file":"","transparent":false,"opacity":1,"texture":"53_5.png"}},"18":{"2":{"x":18,"y":"3","z":"2","hex":"#634830","rgb":[99,72,48],"name":"Spruce Wood","mat_id":"30","file":"","transparent":false,"opacity":1,"texture":"17_1.png"},"3":{"x":18,"y":"3","z":"3","hex":"#b88830","rgb":[184,136,48],"name":"Oak Wood Plank","mat_id":"19","file":"textures\/5_0.png","transparent":false,"opacity":1,"texture":"5_0.png"},"4":{"x":18,"y":"3","z":"4","hex":"#634830","rgb":[99,72,48],"name":"Spruce Wood","mat_id":"30","file":"","transparent":false,"opacity":1,"texture":"17_1.png"}},"13":{"3":{"x":13,"y":"3","z":"3","hex":"#b88830","rgb":[184,136,48],"name":"Oak Wood Plank","mat_id":"19","file":"textures\/5_0.png","transparent":false,"opacity":1,"texture":"5_0.png"}},"14":{"3":{"x":14,"y":"3","z":"3","hex":"#b88830","rgb":[184,136,48],"name":"Oak Wood Plank","mat_id":"19","file":"textures\/5_0.png","transparent":false,"opacity":1,"texture":"5_0.png"}},"9":{"4":{"x":9,"y":"3","z":"4","hex":"#2f8948","rgb":[47,137,72],"name":"Spruce Leaves (No Decay)","mat_id":"329","file":"","transparent":false,"opacity":1,"texture":"18_5.png"},"3":{"x":9,"y":"3","z":"3","hex":"#b88830","rgb":[184,136,48],"name":"Oak Wood Plank","mat_id":"19","file":"textures\/5_0.png","transparent":false,"opacity":1,"texture":"5_0.png"}}},"4":{"5":{"4":{"x":5,"y":"4","z":"4","hex":"#8b6b4e","rgb":[139,107,78],"name":"Oak Wood Stairs (West, Upside-down)","mat_id":"407","file":"","transparent":false,"opacity":1,"texture":"53_5.png"},"2":{"x":5,"y":"4","z":"2","hex":"#8b6b4e","rgb":[139,107,78],"name":"Oak Wood Stairs (East, Upside-down)","mat_id":"406","file":"","transparent":false,"opacity":1,"texture":"53_4.png"}},"16":{"4":{"x":16,"y":"4","z":"4","hex":"#634830","rgb":[99,72,48],"name":"Spruce Wood","mat_id":"30","file":"","transparent":false,"opacity":1,"texture":"17_1.png"},"3":{"x":16,"y":"4","z":"3","hex":"#8b6b4e","rgb":[139,107,78],"name":"Oak Wood Stairs (North, Upside-down)","mat_id":"409","file":"","transparent":false,"opacity":1,"texture":"53_7.png"},"2":{"x":16,"y":"4","z":"2","hex":"#634830","rgb":[99,72,48],"name":"Spruce Wood","mat_id":"30","file":"","transparent":false,"opacity":1,"texture":"17_1.png"}},"15":{"3":{"x":15,"y":"4","z":"3","hex":"#b88830","rgb":[184,136,48],"name":"Oak Wood Plank","mat_id":"19","file":"textures\/5_0.png","transparent":false,"opacity":1,"texture":"5_0.png"}},"18":{"2":{"x":18,"y":"4","z":"2","hex":"#634830","rgb":[99,72,48],"name":"Spruce Wood","mat_id":"30","file":"","transparent":false,"opacity":1,"texture":"17_1.png"},"3":{"x":18,"y":"4","z":"3","hex":"#8b6b4e","rgb":[139,107,78],"name":"Oak Wood Stairs (South, Upside-down)","mat_id":"408","file":"","transparent":false,"opacity":1,"texture":"53_6.png"},"4":{"x":18,"y":"4","z":"4","hex":"#634830","rgb":[99,72,48],"name":"Spruce Wood","mat_id":"30","file":"","transparent":false,"opacity":1,"texture":"17_1.png"}},"17":{"2":{"x":17,"y":"4","z":"2","hex":"#8b6b4e","rgb":[139,107,78],"name":"Oak Wood Stairs (East, Upside-down)","mat_id":"406","file":"","transparent":false,"opacity":1,"texture":"53_4.png"},"4":{"x":17,"y":"4","z":"4","hex":"#8b6b4e","rgb":[139,107,78],"name":"Oak Wood Stairs (West, Upside-down)","mat_id":"407","file":"","transparent":false,"opacity":1,"texture":"53_5.png"}},"4":{"4":{"x":4,"y":"4","z":"4","hex":"#634830","rgb":[99,72,48],"name":"Spruce Wood","mat_id":"30","file":"","transparent":false,"opacity":1,"texture":"17_1.png"},"3":{"x":4,"y":"4","z":"3","hex":"#8b6b4e","rgb":[139,107,78],"name":"Oak Wood Stairs (North, Upside-down)","mat_id":"409","file":"","transparent":false,"opacity":1,"texture":"53_7.png"},"2":{"x":4,"y":"4","z":"2","hex":"#634830","rgb":[99,72,48],"name":"Spruce Wood","mat_id":"30","file":"","transparent":false,"opacity":1,"texture":"17_1.png"}},"14":{"3":{"x":14,"y":"4","z":"3","hex":"#8b6b4e","rgb":[139,107,78],"name":"Oak Wood Stairs (West, Upside-down)","mat_id":"407","file":"","transparent":false,"opacity":1,"texture":"53_5.png"}},"13":{"3":{"x":13,"y":"4","z":"3","hex":"#8b6b4e","rgb":[139,107,78],"name":"Oak Wood Stairs (East, Upside-down)","mat_id":"406","file":"","transparent":false,"opacity":1,"texture":"53_4.png"}},"11":{"4":{"x":11,"y":"4","z":"4","hex":"#c9b62c","rgb":[201,182,44],"name":"Torch (Facing East)","mat_id":"446","file":"","transparent":false,"opacity":1,"texture":"50_1.png"},"3":{"x":11,"y":"4","z":"3","hex":"#b88830","rgb":[184,136,48],"name":"Oak Wood Plank","mat_id":"19","file":"textures\/5_0.png","transparent":false,"opacity":1,"texture":"5_0.png"},"2":{"x":11,"y":"4","z":"2","hex":"#c9b62c","rgb":[201,182,44],"name":"Torch (Facing West)","mat_id":"447","file":"","transparent":false,"opacity":1,"texture":"50_2.png"}},"7":{"3":{"x":7,"y":"4","z":"3","hex":"#b88830","rgb":[184,136,48],"name":"Oak Wood Plank","mat_id":"19","file":"textures\/5_0.png","transparent":false,"opacity":1,"texture":"5_0.png"}},"10":{"3":{"x":10,"y":"4","z":"3","hex":"#b88830","rgb":[184,136,48],"name":"Oak Wood Plank","mat_id":"19","file":"textures\/5_0.png","transparent":false,"opacity":1,"texture":"5_0.png"}},"9":{"3":{"x":9,"y":"4","z":"3","hex":"#b88830","rgb":[184,136,48],"name":"Oak Wood Plank","mat_id":"19","file":"textures\/5_0.png","transparent":false,"opacity":1,"texture":"5_0.png"}},"6":{"2":{"x":6,"y":"4","z":"2","hex":"#634830","rgb":[99,72,48],"name":"Spruce Wood","mat_id":"30","file":"","transparent":false,"opacity":1,"texture":"17_1.png"},"3":{"x":6,"y":"4","z":"3","hex":"#b88830","rgb":[184,136,48],"name":"Oak Wood Plank","mat_id":"19","file":"textures\/5_0.png","transparent":false,"opacity":1,"texture":"5_0.png"},"4":{"x":6,"y":"4","z":"4","hex":"#634830","rgb":[99,72,48],"name":"Spruce Wood","mat_id":"30","file":"","transparent":false,"opacity":1,"texture":"17_1.png"}},"12":{"3":{"x":12,"y":"4","z":"3","hex":"#b88830","rgb":[184,136,48],"name":"Oak Wood Plank","mat_id":"19","file":"textures\/5_0.png","transparent":false,"opacity":1,"texture":"5_0.png"}},"8":{"3":{"x":8,"y":"4","z":"3","hex":"#8b6b4e","rgb":[139,107,78],"name":"Oak Wood Stairs (East, Upside-down)","mat_id":"406","file":"","transparent":false,"opacity":1,"texture":"53_4.png"}}},"5":{"12":{"3":{"x":12,"y":"5","z":"3","hex":"#25100b","rgb":[37,16,11],"name":"Dark Oak Fence","mat_id":"910","file":"","transparent":false,"opacity":1,"texture":"191_0.png"}},"13":{"3":{"x":13,"y":"5","z":"3","hex":"#b88830","rgb":[184,136,48],"name":"Oak Wood Slab (Bottom)","mat_id":"205","file":"","transparent":false,"opacity":1,"texture":"126_0.png"}},"17":{"4":{"x":17,"y":"5","z":"4","hex":"#8b6b4e","rgb":[139,107,78],"name":"Oak Wood Stairs (West, Normal)","mat_id":"297","file":"","transparent":false,"opacity":1,"texture":"53_1.png"},"2":{"x":17,"y":"5","z":"2","hex":"#8b6b4e","rgb":[139,107,78],"name":"Oak Wood Stairs (East, Normal)","mat_id":"101","file":"","transparent":false,"opacity":1,"texture":"53_0.png"},"3":{"x":17,"y":"5","z":"3","hex":"#b88830","rgb":[184,136,48],"name":"Oak Wood Plank","mat_id":"19","file":"textures\/5_0.png","transparent":false,"opacity":1,"texture":"5_0.png"}},"5":{"4":{"x":5,"y":"5","z":"4","hex":"#8b6b4e","rgb":[139,107,78],"name":"Oak Wood Stairs (West, Normal)","mat_id":"297","file":"","transparent":false,"opacity":1,"texture":"53_1.png"},"2":{"x":5,"y":"5","z":"2","hex":"#8b6b4e","rgb":[139,107,78],"name":"Oak Wood Stairs (East, Normal)","mat_id":"101","file":"","transparent":false,"opacity":1,"texture":"53_0.png"},"3":{"x":5,"y":"5","z":"3","hex":"#b88830","rgb":[184,136,48],"name":"Oak Wood Plank","mat_id":"19","file":"textures\/5_0.png","transparent":false,"opacity":1,"texture":"5_0.png"}},"4":{"4":{"x":4,"y":"5","z":"4","hex":"#634830","rgb":[99,72,48],"name":"Spruce Wood","mat_id":"30","file":"","transparent":false,"opacity":1,"texture":"17_1.png"},"3":{"x":4,"y":"5","z":"3","hex":"#8b6b4e","rgb":[139,107,78],"name":"Oak Wood Stairs (North, Normal)","mat_id":"296","file":"","transparent":false,"opacity":1,"texture":"53_3.png"},"2":{"x":4,"y":"5","z":"2","hex":"#634830","rgb":[99,72,48],"name":"Spruce Wood","mat_id":"30","file":"","transparent":false,"opacity":1,"texture":"17_1.png"}},"7":{"3":{"x":7,"y":"5","z":"3","hex":"#b88830","rgb":[184,136,48],"name":"Oak Wood Slab (Bottom)","mat_id":"205","file":"","transparent":false,"opacity":1,"texture":"126_0.png"}},"6":{"2":{"x":6,"y":"5","z":"2","hex":"#634830","rgb":[99,72,48],"name":"Spruce Wood","mat_id":"30","file":"","transparent":false,"opacity":1,"texture":"17_1.png"},"4":{"x":6,"y":"5","z":"4","hex":"#634830","rgb":[99,72,48],"name":"Spruce Wood","mat_id":"30","file":"","transparent":false,"opacity":1,"texture":"17_1.png"},"3":{"x":6,"y":"5","z":"3","hex":"#8b6b4e","rgb":[139,107,78],"name":"Oak Wood Stairs (South, Normal)","mat_id":"298","file":"","transparent":false,"opacity":1,"texture":"53_2.png"}},"18":{"4":{"x":18,"y":"5","z":"4","hex":"#634830","rgb":[99,72,48],"name":"Spruce Wood","mat_id":"30","file":"","transparent":false,"opacity":1,"texture":"17_1.png"},"2":{"x":18,"y":"5","z":"2","hex":"#634830","rgb":[99,72,48],"name":"Spruce Wood","mat_id":"30","file":"","transparent":false,"opacity":1,"texture":"17_1.png"},"3":{"x":18,"y":"5","z":"3","hex":"#8b6b4e","rgb":[139,107,78],"name":"Oak Wood Stairs (South, Normal)","mat_id":"298","file":"","transparent":false,"opacity":1,"texture":"53_2.png"}},"14":{"3":{"x":14,"y":"5","z":"3","hex":"#49371f","rgb":[73,55,31],"name":"Spruce Fence","mat_id":"907","file":"","transparent":false,"opacity":1,"texture":"188_0.png"}},"15":{"3":{"x":15,"y":"5","z":"3","hex":"#b88830","rgb":[184,136,48],"name":"Oak Wood Slab (Bottom)","mat_id":"205","file":"","transparent":false,"opacity":1,"texture":"126_0.png"}},"8":{"3":{"x":8,"y":"5","z":"3","hex":"#49371f","rgb":[73,55,31],"name":"Spruce Fence","mat_id":"907","file":"","transparent":false,"opacity":1,"texture":"188_0.png"}},"10":{"3":{"x":10,"y":"5","z":"3","hex":"#25100b","rgb":[37,16,11],"name":"Dark Oak Fence","mat_id":"910","file":"","transparent":false,"opacity":1,"texture":"191_0.png"}},"11":{"3":{"x":11,"y":"5","z":"3","hex":"#b88830","rgb":[184,136,48],"name":"Oak Wood Slab (Bottom)","mat_id":"205","file":"","transparent":false,"opacity":1,"texture":"126_0.png"}},"9":{"3":{"x":9,"y":"5","z":"3","hex":"#b88830","rgb":[184,136,48],"name":"Oak Wood Slab (Bottom)","mat_id":"205","file":"","transparent":false,"opacity":1,"texture":"126_0.png"}},"16":{"4":{"x":16,"y":"5","z":"4","hex":"#634830","rgb":[99,72,48],"name":"Spruce Wood","mat_id":"30","file":"","transparent":false,"opacity":1,"texture":"17_1.png"},"3":{"x":16,"y":"5","z":"3","hex":"#8b6b4e","rgb":[139,107,78],"name":"Oak Wood Stairs (North, Normal)","mat_id":"296","file":"","transparent":false,"opacity":1,"texture":"53_3.png"},"2":{"x":16,"y":"5","z":"2","hex":"#634830","rgb":[99,72,48],"name":"Spruce Wood","mat_id":"30","file":"","transparent":false,"opacity":1,"texture":"17_1.png"}}},"6":{"6":{"2":{"x":6,"y":"6","z":"2","hex":"#25100b","rgb":[37,16,11],"name":"Dark Oak Fence","mat_id":"910","file":"","transparent":false,"opacity":1,"texture":"191_0.png"},"4":{"x":6,"y":"6","z":"4","hex":"#49371f","rgb":[73,55,31],"name":"Spruce Fence","mat_id":"907","file":"","transparent":false,"opacity":1,"texture":"188_0.png"}},"18":{"2":{"x":18,"y":"6","z":"2","hex":"#25100b","rgb":[37,16,11],"name":"Dark Oak Fence","mat_id":"910","file":"","transparent":false,"opacity":1,"texture":"191_0.png"},"4":{"x":18,"y":"6","z":"4","hex":"#49371f","rgb":[73,55,31],"name":"Spruce Fence","mat_id":"907","file":"","transparent":false,"opacity":1,"texture":"188_0.png"}},"4":{"4":{"x":4,"y":"6","z":"4","hex":"#25100b","rgb":[37,16,11],"name":"Dark Oak Fence","mat_id":"910","file":"","transparent":false,"opacity":1,"texture":"191_0.png"},"2":{"x":4,"y":"6","z":"2","hex":"#49371f","rgb":[73,55,31],"name":"Spruce Fence","mat_id":"907","file":"","transparent":false,"opacity":1,"texture":"188_0.png"}},"5":{"3":{"x":5,"y":"6","z":"3","hex":"#6e6868","rgb":[110,104,104],"name":"Cobblestone Wall","mat_id":"223","file":"","transparent":false,"opacity":1,"texture":"139_0.png"}},"16":{"2":{"x":16,"y":"6","z":"2","hex":"#49371f","rgb":[73,55,31],"name":"Spruce Fence","mat_id":"907","file":"","transparent":false,"opacity":1,"texture":"188_0.png"},"4":{"x":16,"y":"6","z":"4","hex":"#49371f","rgb":[73,55,31],"name":"Spruce Fence","mat_id":"907","file":"","transparent":false,"opacity":1,"texture":"188_0.png"}},"17":{"3":{"x":17,"y":"6","z":"3","hex":"#6e6868","rgb":[110,104,104],"name":"Cobblestone Wall","mat_id":"223","file":"","transparent":false,"opacity":1,"texture":"139_0.png"}}},"7":{"2":{"4":{"x":2,"y":"7","z":"4","hex":"#14198a","rgb":[20,25,138],"name":"Blue Wool","mat_id":"69","file":"textures\/35_11.png","transparent":false,"opacity":1,"texture":"35_11.png"}},"5":{"3":{"x":5,"y":"7","z":"3","hex":"#25100b","rgb":[37,16,11],"name":"Dark Oak Fence","mat_id":"910","file":"","transparent":false,"opacity":1,"texture":"191_0.png"}},"1":{"4":{"x":1,"y":"7","z":"4","hex":"#14198a","rgb":[20,25,138],"name":"Blue Wool","mat_id":"69","file":"textures\/35_11.png","transparent":false,"opacity":1,"texture":"35_11.png"}},"14":{"4":{"x":14,"y":"7","z":"4","hex":"#14198a","rgb":[20,25,138],"name":"Blue Wool","mat_id":"69","file":"textures\/35_11.png","transparent":false,"opacity":1,"texture":"35_11.png"}},"17":{"3":{"x":17,"y":"7","z":"3","hex":"#25100b","rgb":[37,16,11],"name":"Dark Oak Fence","mat_id":"910","file":"","transparent":false,"opacity":1,"texture":"191_0.png"}},"13":{"4":{"x":13,"y":"7","z":"4","hex":"#14198a","rgb":[20,25,138],"name":"Blue Wool","mat_id":"69","file":"textures\/35_11.png","transparent":false,"opacity":1,"texture":"35_11.png"}}},"8":{"3":{"3":{"x":3,"y":"8","z":"3","hex":"#14198a","rgb":[20,25,138],"name":"Blue Wool","mat_id":"69","file":"textures\/35_11.png","transparent":false,"opacity":1,"texture":"35_11.png"}},"15":{"3":{"x":15,"y":"8","z":"3","hex":"#14198a","rgb":[20,25,138],"name":"Blue Wool","mat_id":"69","file":"textures\/35_11.png","transparent":false,"opacity":1,"texture":"35_11.png"}},"16":{"3":{"x":16,"y":"8","z":"3","hex":"#14198a","rgb":[20,25,138],"name":"Blue Wool","mat_id":"69","file":"textures\/35_11.png","transparent":false,"opacity":1,"texture":"35_11.png"}},"2":{"4":{"x":2,"y":"8","z":"4","hex":"#f7f7f7","rgb":[247,247,247],"name":"White Wool","mat_id":"40","file":"textures\/35_0.png","transparent":false,"opacity":1,"texture":"35_0.png"}},"17":{"3":{"x":17,"y":"8","z":"3","hex":"#49371f","rgb":[73,55,31],"name":"Spruce Fence","mat_id":"907","file":"","transparent":false,"opacity":1,"texture":"188_0.png"}},"5":{"3":{"x":5,"y":"8","z":"3","hex":"#25100b","rgb":[37,16,11],"name":"Dark Oak Fence","mat_id":"910","file":"","transparent":false,"opacity":1,"texture":"191_0.png"}},"14":{"4":{"x":14,"y":"8","z":"4","hex":"#f7f7f7","rgb":[247,247,247],"name":"White Wool","mat_id":"40","file":"textures\/35_0.png","transparent":false,"opacity":1,"texture":"35_0.png"}},"4":{"3":{"x":4,"y":"8","z":"3","hex":"#14198a","rgb":[20,25,138],"name":"Blue Wool","mat_id":"69","file":"textures\/35_11.png","transparent":false,"opacity":1,"texture":"35_11.png"}}},"9":{"17":{"3":{"x":17,"y":"9","z":"3","hex":"#49371f","rgb":[73,55,31],"name":"Spruce Fence","mat_id":"907","file":"","transparent":false,"opacity":1,"texture":"188_0.png"}},"5":{"3":{"x":5,"y":"9","z":"3","hex":"#49371f","rgb":[73,55,31],"name":"Spruce Fence","mat_id":"907","file":"","transparent":false,"opacity":1,"texture":"188_0.png"}},"4":{"3":{"x":4,"y":"9","z":"3","hex":"#f7f7f7","rgb":[247,247,247],"name":"White Wool","mat_id":"40","file":"textures\/35_0.png","transparent":false,"opacity":1,"texture":"35_0.png"}},"16":{"3":{"x":16,"y":"9","z":"3","hex":"#f7f7f7","rgb":[247,247,247],"name":"White Wool","mat_id":"40","file":"textures\/35_0.png","transparent":false,"opacity":1,"texture":"35_0.png"}}}}