{"1":{"10":{"13":{"x":10,"y":"1","z":"13","hex":"#706c6c","rgb":[112,108,108],"name":"Stone Bricks","mat_id":"169","file":"","transparent":false,"opacity":1,"texture":"98_0.png"},"14":{"x":10,"y":"1","z":"14","hex":"#a7a7a7","rgb":[167,167,167],"name":"Stone Brick Stairs (South, Upside-down)","mat_id":"486","file":"","transparent":false,"opacity":1,"texture":"109_6.png"}},"2":{"13":{"x":2,"y":"1","z":"13","hex":"#706c6c","rgb":[112,108,108],"name":"Stone Bricks","mat_id":"169","file":"","transparent":false,"opacity":1,"texture":"98_0.png"},"14":{"x":2,"y":"1","z":"14","hex":"#a7a7a7","rgb":[167,167,167],"name":"Stone Brick Stairs (South, Upside-down)","mat_id":"486","file":"","transparent":false,"opacity":1,"texture":"109_6.png"}}},"2":{"10":{"14":{"x":10,"y":"2","z":"14","hex":"#706c6c","rgb":[112,108,108],"name":"Stone Bricks","mat_id":"169","file":"","transparent":false,"opacity":1,"texture":"98_0.png"},"13":{"x":10,"y":"2","z":"13","hex":"#706c6c","rgb":[112,108,108],"name":"Stone Bricks","mat_id":"169","file":"","transparent":false,"opacity":1,"texture":"98_0.png"}},"2":{"14":{"x":2,"y":"2","z":"14","hex":"#706c6c","rgb":[112,108,108],"name":"Stone Bricks","mat_id":"169","file":"","transparent":false,"opacity":1,"texture":"98_0.png"},"13":{"x":2,"y":"2","z":"13","hex":"#706c6c","rgb":[112,108,108],"name":"Stone Bricks","mat_id":"169","file":"","transparent":false,"opacity":1,"texture":"98_0.png"}}},"3":{"2":{"14":{"x":2,"y":"3","z":"14","hex":"#706c6c","rgb":[112,108,108],"name":"Stone Bricks","mat_id":"169","file":"","transparent":false,"opacity":1,"texture":"98_0.png"},"13":{"x":2,"y":"3","z":"13","hex":"#706c6c","rgb":[112,108,108],"name":"Stone Bricks","mat_id":"169","file":"","transparent":false,"opacity":1,"texture":"98_0.png"},"15":{"x":2,"y":"3","z":"15","hex":"#a7a7a7","rgb":[167,167,167],"name":"Stone Brick Stairs (South, Upside-down)","mat_id":"486","file":"","transparent":false,"opacity":1,"texture":"109_6.png"}},"10":{"15":{"x":10,"y":"3","z":"15","hex":"#a7a7a7","rgb":[167,167,167],"name":"Stone Brick Stairs (South, Upside-down)","mat_id":"486","file":"","transparent":false,"opacity":1,"texture":"109_6.png"},"14":{"x":10,"y":"3","z":"14","hex":"#706c6c","rgb":[112,108,108],"name":"Stone Bricks","mat_id":"169","file":"","transparent":false,"opacity":1,"texture":"98_0.png"},"13":{"x":10,"y":"3","z":"13","hex":"#706c6c","rgb":[112,108,108],"name":"Stone Bricks","mat_id":"169","file":"","transparent":false,"opacity":1,"texture":"98_0.png"}}},"4":{"2":{"15":{"x":2,"y":"4","z":"15","hex":"#706c6c","rgb":[112,108,108],"name":"Stone Bricks","mat_id":"169","file":"","transparent":false,"opacity":1,"texture":"98_0.png"},"13":{"x":2,"y":"4","z":"13","hex":"#706c6c","rgb":[112,108,108],"name":"Stone Bricks","mat_id":"169","file":"","transparent":false,"opacity":1,"texture":"98_0.png"},"14":{"x":2,"y":"4","z":"14","hex":"#706c6c","rgb":[112,108,108],"name":"Stone Bricks","mat_id":"169","file":"","transparent":false,"opacity":1,"texture":"98_0.png"}},"10":{"14":{"x":10,"y":"4","z":"14","hex":"#706c6c","rgb":[112,108,108],"name":"Stone Bricks","mat_id":"169","file":"","transparent":false,"opacity":1,"texture":"98_0.png"},"13":{"x":10,"y":"4","z":"13","hex":"#706c6c","rgb":[112,108,108],"name":"Stone Bricks","mat_id":"169","file":"","transparent":false,"opacity":1,"texture":"98_0.png"},"15":{"x":10,"y":"4","z":"15","hex":"#706c6c","rgb":[112,108,108],"name":"Stone Bricks","mat_id":"169","file":"","transparent":false,"opacity":1,"texture":"98_0.png"}}},"5":{"6":{"12":{"x":6,"y":"5","z":"12","hex":"#000000","rgb":[0,0,0],"name":"Nether Brick Slab (Upper)","mat_id":"499","file":"","transparent":false,"opacity":1,"texture":"44_14.png"},"11":{"x":6,"y":"5","z":"11","hex":"#000000","rgb":[0,0,0],"name":"Nether Brick Slab (Upper)","mat_id":"499","file":"","transparent":false,"opacity":1,"texture":"44_14.png"},"13":{"x":6,"y":"5","z":"13","hex":"#000000","rgb":[0,0,0],"name":"Nether Brick Slab (Upper)","mat_id":"499","file":"","transparent":false,"opacity":1,"texture":"44_14.png"},"14":{"x":6,"y":"5","z":"14","hex":"#000000","rgb":[0,0,0],"name":"Nether Brick Slab (Upper)","mat_id":"499","file":"","transparent":false,"opacity":1,"texture":"44_14.png"},"15":{"x":6,"y":"5","z":"15","hex":"#000000","rgb":[0,0,0],"name":"Nether Brick Slab (Upper)","mat_id":"499","file":"","transparent":false,"opacity":1,"texture":"44_14.png"}},"2":{"15":{"x":2,"y":"5","z":"15","hex":"#706c6c","rgb":[112,108,108],"name":"Stone Bricks","mat_id":"169","file":"","transparent":false,"opacity":1,"texture":"98_0.png"},"14":{"x":2,"y":"5","z":"14","hex":"#706c6c","rgb":[112,108,108],"name":"Stone Bricks","mat_id":"169","file":"","transparent":false,"opacity":1,"texture":"98_0.png"},"13":{"x":2,"y":"5","z":"13","hex":"#706c6c","rgb":[112,108,108],"name":"Stone Bricks","mat_id":"169","file":"","transparent":false,"opacity":1,"texture":"98_0.png"}},"10":{"14":{"x":10,"y":"5","z":"14","hex":"#706c6c","rgb":[112,108,108],"name":"Stone Bricks","mat_id":"169","file":"","transparent":false,"opacity":1,"texture":"98_0.png"},"13":{"x":10,"y":"5","z":"13","hex":"#706c6c","rgb":[112,108,108],"name":"Stone Bricks","mat_id":"169","file":"","transparent":false,"opacity":1,"texture":"98_0.png"},"15":{"x":10,"y":"5","z":"15","hex":"#706c6c","rgb":[112,108,108],"name":"Stone Bricks","mat_id":"169","file":"","transparent":false,"opacity":1,"texture":"98_0.png"}},"11":{"14":{"x":11,"y":"5","z":"14","hex":"#591b1b","rgb":[89,27,27],"name":"Nether Brick Fence","mat_id":"187","file":"","transparent":false,"opacity":1,"texture":"113_0.png"}},"1":{"14":{"x":1,"y":"5","z":"14","hex":"#591b1b","rgb":[89,27,27],"name":"Nether Brick Fence","mat_id":"187","file":"","transparent":false,"opacity":1,"texture":"113_0.png"}}},"6":{"7":{"5":{"x":7,"y":"6","z":"5","hex":"#000000","rgb":[0,0,0],"name":"Stone Slab (Upper)","mat_id":"493","file":"","transparent":false,"opacity":1,"texture":"44_8.png"},"7":{"x":7,"y":"6","z":"7","hex":"#000000","rgb":[0,0,0],"name":"Stone Slab (Upper)","mat_id":"493","file":"","transparent":false,"opacity":1,"texture":"44_8.png"},"6":{"x":7,"y":"6","z":"6","hex":"#000000","rgb":[0,0,0],"name":"Stone Slab (Upper)","mat_id":"493","file":"","transparent":false,"opacity":1,"texture":"44_8.png"},"10":{"x":7,"y":"6","z":"10","hex":"#545454","rgb":[84,84,84],"name":"Smooth Double Stone Slab","mat_id":"1643","file":"","transparent":false,"opacity":1,"texture":"43_8.png"},"11":{"x":7,"y":"6","z":"11","hex":"#545454","rgb":[84,84,84],"name":"Smooth Double Stone Slab","mat_id":"1643","file":"","transparent":false,"opacity":1,"texture":"43_8.png"},"9":{"x":7,"y":"6","z":"9","hex":"#545454","rgb":[84,84,84],"name":"Smooth Double Stone Slab","mat_id":"1643","file":"","transparent":false,"opacity":1,"texture":"43_8.png"},"12":{"x":7,"y":"6","z":"12","hex":"#545454","rgb":[84,84,84],"name":"Smooth Double Stone Slab","mat_id":"1643","file":"","transparent":false,"opacity":1,"texture":"43_8.png"},"13":{"x":7,"y":"6","z":"13","hex":"#545454","rgb":[84,84,84],"name":"Smooth Double Stone Slab","mat_id":"1643","file":"","transparent":false,"opacity":1,"texture":"43_8.png"},"14":{"x":7,"y":"6","z":"14","hex":"#333107","rgb":[51,49,7],"name":"Nether Brick","mat_id":"186","file":"textures\/112_0.png","transparent":false,"opacity":1,"texture":"112_0.png"},"15":{"x":7,"y":"6","z":"15","hex":"#333107","rgb":[51,49,7],"name":"Nether Brick","mat_id":"186","file":"textures\/112_0.png","transparent":false,"opacity":1,"texture":"112_0.png"},"18":{"x":7,"y":"6","z":"18","hex":"#a2e098","rgb":[162,224,152],"name":"Lime Stained Glass Pane","mat_id":"265","file":"","transparent":true,"opacity":0.5,"texture":"160_5.png"},"19":{"x":7,"y":"6","z":"19","hex":"#a2e098","rgb":[162,224,152],"name":"Lime Stained Glass Pane","mat_id":"265","file":"","transparent":true,"opacity":0.5,"texture":"160_5.png"},"8":{"x":7,"y":"6","z":"8","hex":"#545454","rgb":[84,84,84],"name":"Smooth Double Stone Slab","mat_id":"1643","file":"","transparent":false,"opacity":1,"texture":"43_8.png"}},"4":{"7":{"x":4,"y":"6","z":"7","hex":"#000000","rgb":[0,0,0],"name":"Stone Slab (Upper)","mat_id":"493","file":"","transparent":false,"opacity":1,"texture":"44_8.png"},"8":{"x":4,"y":"6","z":"8","hex":"#000000","rgb":[0,0,0],"name":"Stone Slab (Upper)","mat_id":"493","file":"","transparent":false,"opacity":1,"texture":"44_8.png"},"9":{"x":4,"y":"6","z":"9","hex":"#000000","rgb":[0,0,0],"name":"Stone Slab (Upper)","mat_id":"493","file":"","transparent":false,"opacity":1,"texture":"44_8.png"},"10":{"x":4,"y":"6","z":"10","hex":"#000000","rgb":[0,0,0],"name":"Stone Slab (Upper)","mat_id":"493","file":"","transparent":false,"opacity":1,"texture":"44_8.png"},"13":{"x":4,"y":"6","z":"13","hex":"#000000","rgb":[0,0,0],"name":"Stone Slab (Upper)","mat_id":"493","file":"","transparent":false,"opacity":1,"texture":"44_8.png"},"12":{"x":4,"y":"6","z":"12","hex":"#000000","rgb":[0,0,0],"name":"Stone Slab (Upper)","mat_id":"493","file":"","transparent":false,"opacity":1,"texture":"44_8.png"},"11":{"x":4,"y":"6","z":"11","hex":"#000000","rgb":[0,0,0],"name":"Stone Slab (Upper)","mat_id":"493","file":"","transparent":false,"opacity":1,"texture":"44_8.png"}},"5":{"11":{"x":5,"y":"6","z":"11","hex":"#545454","rgb":[84,84,84],"name":"Smooth Double Stone Slab","mat_id":"1643","file":"","transparent":false,"opacity":1,"texture":"43_8.png"},"12":{"x":5,"y":"6","z":"12","hex":"#545454","rgb":[84,84,84],"name":"Smooth Double Stone Slab","mat_id":"1643","file":"","transparent":false,"opacity":1,"texture":"43_8.png"},"17":{"x":5,"y":"6","z":"17","hex":"#a2e098","rgb":[162,224,152],"name":"Lime Stained Glass Pane","mat_id":"265","file":"","transparent":true,"opacity":0.5,"texture":"160_5.png"},"15":{"x":5,"y":"6","z":"15","hex":"#333107","rgb":[51,49,7],"name":"Nether Brick","mat_id":"186","file":"textures\/112_0.png","transparent":false,"opacity":1,"texture":"112_0.png"},"14":{"x":5,"y":"6","z":"14","hex":"#333107","rgb":[51,49,7],"name":"Nether Brick","mat_id":"186","file":"textures\/112_0.png","transparent":false,"opacity":1,"texture":"112_0.png"},"10":{"x":5,"y":"6","z":"10","hex":"#545454","rgb":[84,84,84],"name":"Smooth Double Stone Slab","mat_id":"1643","file":"","transparent":false,"opacity":1,"texture":"43_8.png"},"9":{"x":5,"y":"6","z":"9","hex":"#545454","rgb":[84,84,84],"name":"Smooth Double Stone Slab","mat_id":"1643","file":"","transparent":false,"opacity":1,"texture":"43_8.png"},"8":{"x":5,"y":"6","z":"8","hex":"#545454","rgb":[84,84,84],"name":"Smooth Double Stone Slab","mat_id":"1643","file":"","transparent":false,"opacity":1,"texture":"43_8.png"},"7":{"x":5,"y":"6","z":"7","hex":"#000000","rgb":[0,0,0],"name":"Stone Slab (Upper)","mat_id":"493","file":"","transparent":false,"opacity":1,"texture":"44_8.png"},"6":{"x":5,"y":"6","z":"6","hex":"#000000","rgb":[0,0,0],"name":"Stone Slab (Upper)","mat_id":"493","file":"","transparent":false,"opacity":1,"texture":"44_8.png"},"5":{"x":5,"y":"6","z":"5","hex":"#000000","rgb":[0,0,0],"name":"Stone Slab (Upper)","mat_id":"493","file":"","transparent":false,"opacity":1,"texture":"44_8.png"},"13":{"x":5,"y":"6","z":"13","hex":"#545454","rgb":[84,84,84],"name":"Smooth Double Stone Slab","mat_id":"1643","file":"","transparent":false,"opacity":1,"texture":"43_8.png"}},"6":{"12":{"x":6,"y":"6","z":"12","hex":"#545454","rgb":[84,84,84],"name":"Smooth Double Stone Slab","mat_id":"1643","file":"","transparent":false,"opacity":1,"texture":"43_8.png"},"3":{"x":6,"y":"6","z":"3","hex":"#000000","rgb":[0,0,0],"name":"Stone Slab (Upper)","mat_id":"493","file":"","transparent":false,"opacity":1,"texture":"44_8.png"},"4":{"x":6,"y":"6","z":"4","hex":"#000000","rgb":[0,0,0],"name":"Stone Slab (Upper)","mat_id":"493","file":"","transparent":false,"opacity":1,"texture":"44_8.png"},"5":{"x":6,"y":"6","z":"5","hex":"#000000","rgb":[0,0,0],"name":"Stone Slab (Upper)","mat_id":"493","file":"","transparent":false,"opacity":1,"texture":"44_8.png"},"6":{"x":6,"y":"6","z":"6","hex":"#545454","rgb":[84,84,84],"name":"Smooth Double Stone Slab","mat_id":"1643","file":"","transparent":false,"opacity":1,"texture":"43_8.png"},"7":{"x":6,"y":"6","z":"7","hex":"#545454","rgb":[84,84,84],"name":"Smooth Double Stone Slab","mat_id":"1643","file":"","transparent":false,"opacity":1,"texture":"43_8.png"},"8":{"x":6,"y":"6","z":"8","hex":"#545454","rgb":[84,84,84],"name":"Smooth Double Stone Slab","mat_id":"1643","file":"","transparent":false,"opacity":1,"texture":"43_8.png"},"9":{"x":6,"y":"6","z":"9","hex":"#545454","rgb":[84,84,84],"name":"Smooth Double Stone Slab","mat_id":"1643","file":"","transparent":false,"opacity":1,"texture":"43_8.png"},"10":{"x":6,"y":"6","z":"10","hex":"#545454","rgb":[84,84,84],"name":"Smooth Double Stone Slab","mat_id":"1643","file":"","transparent":false,"opacity":1,"texture":"43_8.png"},"14":{"x":6,"y":"6","z":"14","hex":"#6b6b6b","rgb":[107,107,107],"name":"Gray Wool","mat_id":"66","file":"textures\/35_7.png","transparent":false,"opacity":1,"texture":"35_7.png"},"15":{"x":6,"y":"6","z":"15","hex":"#6b6b6b","rgb":[107,107,107],"name":"Gray Wool","mat_id":"66","file":"textures\/35_7.png","transparent":false,"opacity":1,"texture":"35_7.png"},"13":{"x":6,"y":"6","z":"13","hex":"#545454","rgb":[84,84,84],"name":"Smooth Double Stone Slab","mat_id":"1643","file":"","transparent":false,"opacity":1,"texture":"43_8.png"},"20":{"x":6,"y":"6","z":"20","hex":"#a2e098","rgb":[162,224,152],"name":"Lime Stained Glass Pane","mat_id":"265","file":"","transparent":true,"opacity":0.5,"texture":"160_5.png"},"19":{"x":6,"y":"6","z":"19","hex":"#a2e098","rgb":[162,224,152],"name":"Lime Stained Glass Pane","mat_id":"265","file":"","transparent":true,"opacity":0.5,"texture":"160_5.png"},"18":{"x":6,"y":"6","z":"18","hex":"#c1ed9e","rgb":[193,237,158],"name":"Lime Stained Glass","mat_id":"151","file":"","transparent":true,"opacity":0.5,"texture":"95_5.png"},"17":{"x":6,"y":"6","z":"17","hex":"#c1ed9e","rgb":[193,237,158],"name":"Lime Stained Glass","mat_id":"151","file":"","transparent":true,"opacity":0.5,"texture":"95_5.png"},"11":{"x":6,"y":"6","z":"11","hex":"#545454","rgb":[84,84,84],"name":"Smooth Double Stone Slab","mat_id":"1643","file":"","transparent":false,"opacity":1,"texture":"43_8.png"},"16":{"x":6,"y":"6","z":"16","hex":"#6b6b6b","rgb":[107,107,107],"name":"Gray Wool","mat_id":"66","file":"textures\/35_7.png","transparent":false,"opacity":1,"texture":"35_7.png"}},"11":{"14":{"x":11,"y":"6","z":"14","hex":"#591b1b","rgb":[89,27,27],"name":"Nether Brick Fence","mat_id":"187","file":"","transparent":false,"opacity":1,"texture":"113_0.png"},"13":{"x":11,"y":"6","z":"13","hex":"#a4a499","rgb":[164,164,153],"name":"Stone Button (Facing West, Inactive)","mat_id":"759","file":"","transparent":false,"opacity":1,"texture":"77_2.png"}},"3":{"11":{"x":3,"y":"6","z":"11","hex":"#000000","rgb":[0,0,0],"name":"Stone Slab (Upper)","mat_id":"493","file":"","transparent":false,"opacity":1,"texture":"44_8.png"},"10":{"x":3,"y":"6","z":"10","hex":"#000000","rgb":[0,0,0],"name":"Stone Slab (Upper)","mat_id":"493","file":"","transparent":false,"opacity":1,"texture":"44_8.png"}},"2":{"13":{"x":2,"y":"6","z":"13","hex":"#6b6b6b","rgb":[107,107,107],"name":"Gray Wool","mat_id":"66","file":"textures\/35_7.png","transparent":false,"opacity":1,"texture":"35_7.png"},"14":{"x":2,"y":"6","z":"14","hex":"#6b6b6b","rgb":[107,107,107],"name":"Gray Wool","mat_id":"66","file":"textures\/35_7.png","transparent":false,"opacity":1,"texture":"35_7.png"},"12":{"x":2,"y":"6","z":"12","hex":"#6b6b6b","rgb":[107,107,107],"name":"Gray Wool","mat_id":"66","file":"textures\/35_7.png","transparent":false,"opacity":1,"texture":"35_7.png"},"15":{"x":2,"y":"6","z":"15","hex":"#400000","rgb":[64,0,0],"name":"Nether Brick Stairs (South, Upside-down)","mat_id":"606","file":"","transparent":false,"opacity":1,"texture":"114_6.png"},"16":{"x":2,"y":"6","z":"16","hex":"#000000","rgb":[0,0,0],"name":"Nether Brick Slab (Upper)","mat_id":"499","file":"","transparent":false,"opacity":1,"texture":"44_14.png"}},"9":{"11":{"x":9,"y":"6","z":"11","hex":"#000000","rgb":[0,0,0],"name":"Stone Slab (Upper)","mat_id":"493","file":"","transparent":false,"opacity":1,"texture":"44_8.png"},"10":{"x":9,"y":"6","z":"10","hex":"#000000","rgb":[0,0,0],"name":"Stone Slab (Upper)","mat_id":"493","file":"","transparent":false,"opacity":1,"texture":"44_8.png"}},"10":{"13":{"x":10,"y":"6","z":"13","hex":"#6b6b6b","rgb":[107,107,107],"name":"Gray Wool","mat_id":"66","file":"textures\/35_7.png","transparent":false,"opacity":1,"texture":"35_7.png"},"16":{"x":10,"y":"6","z":"16","hex":"#000000","rgb":[0,0,0],"name":"Nether Brick Slab (Upper)","mat_id":"499","file":"","transparent":false,"opacity":1,"texture":"44_14.png"},"15":{"x":10,"y":"6","z":"15","hex":"#400000","rgb":[64,0,0],"name":"Nether Brick Stairs (South, Upside-down)","mat_id":"606","file":"","transparent":false,"opacity":1,"texture":"114_6.png"},"14":{"x":10,"y":"6","z":"14","hex":"#6b6b6b","rgb":[107,107,107],"name":"Gray Wool","mat_id":"66","file":"textures\/35_7.png","transparent":false,"opacity":1,"texture":"35_7.png"},"12":{"x":10,"y":"6","z":"12","hex":"#6b6b6b","rgb":[107,107,107],"name":"Gray Wool","mat_id":"66","file":"textures\/35_7.png","transparent":false,"opacity":1,"texture":"35_7.png"}},"1":{"13":{"x":1,"y":"6","z":"13","hex":"#a4a499","rgb":[164,164,153],"name":"Stone Button (Facing East, Inactive)","mat_id":"758","file":"","transparent":false,"opacity":1,"texture":"77_1.png"},"14":{"x":1,"y":"6","z":"14","hex":"#591b1b","rgb":[89,27,27],"name":"Nether Brick Fence","mat_id":"187","file":"","transparent":false,"opacity":1,"texture":"113_0.png"}},"8":{"13":{"x":8,"y":"6","z":"13","hex":"#000000","rgb":[0,0,0],"name":"Stone Slab (Upper)","mat_id":"493","file":"","transparent":false,"opacity":1,"texture":"44_8.png"},"12":{"x":8,"y":"6","z":"12","hex":"#000000","rgb":[0,0,0],"name":"Stone Slab (Upper)","mat_id":"493","file":"","transparent":false,"opacity":1,"texture":"44_8.png"},"11":{"x":8,"y":"6","z":"11","hex":"#000000","rgb":[0,0,0],"name":"Stone Slab (Upper)","mat_id":"493","file":"","transparent":false,"opacity":1,"texture":"44_8.png"},"10":{"x":8,"y":"6","z":"10","hex":"#000000","rgb":[0,0,0],"name":"Stone Slab (Upper)","mat_id":"493","file":"","transparent":false,"opacity":1,"texture":"44_8.png"},"8":{"x":8,"y":"6","z":"8","hex":"#000000","rgb":[0,0,0],"name":"Stone Slab (Upper)","mat_id":"493","file":"","transparent":false,"opacity":1,"texture":"44_8.png"},"9":{"x":8,"y":"6","z":"9","hex":"#000000","rgb":[0,0,0],"name":"Stone Slab (Upper)","mat_id":"493","file":"","transparent":false,"opacity":1,"texture":"44_8.png"},"7":{"x":8,"y":"6","z":"7","hex":"#000000","rgb":[0,0,0],"name":"Stone Slab (Upper)","mat_id":"493","file":"","transparent":false,"opacity":1,"texture":"44_8.png"}}},"7":{"2":{"12":{"x":2,"y":"7","z":"12","hex":"#6b6b6b","rgb":[107,107,107],"name":"Gray Wool","mat_id":"66","file":"textures\/35_7.png","transparent":false,"opacity":1,"texture":"35_7.png"},"16":{"x":2,"y":"7","z":"16","hex":"#333107","rgb":[51,49,7],"name":"Nether Brick","mat_id":"186","file":"textures\/112_0.png","transparent":false,"opacity":1,"texture":"112_0.png"},"15":{"x":2,"y":"7","z":"15","hex":"#333107","rgb":[51,49,7],"name":"Nether Brick","mat_id":"186","file":"textures\/112_0.png","transparent":false,"opacity":1,"texture":"112_0.png"},"14":{"x":2,"y":"7","z":"14","hex":"#6b6b6b","rgb":[107,107,107],"name":"Gray Wool","mat_id":"66","file":"textures\/35_7.png","transparent":false,"opacity":1,"texture":"35_7.png"},"17":{"x":2,"y":"7","z":"17","hex":"#333107","rgb":[51,49,7],"name":"Nether Brick","mat_id":"186","file":"textures\/112_0.png","transparent":false,"opacity":1,"texture":"112_0.png"},"13":{"x":2,"y":"7","z":"13","hex":"#333107","rgb":[51,49,7],"name":"Nether Brick","mat_id":"186","file":"textures\/112_0.png","transparent":false,"opacity":1,"texture":"112_0.png"},"11":{"x":2,"y":"7","z":"11","hex":"#331919","rgb":[51,25,25],"name":"Nether Brick Slab","mat_id":"91","file":"","transparent":false,"opacity":1,"texture":"44_6.png"},"10":{"x":2,"y":"7","z":"10","hex":"#331919","rgb":[51,25,25],"name":"Nether Brick Slab","mat_id":"91","file":"","transparent":false,"opacity":1,"texture":"44_6.png"},"9":{"x":2,"y":"7","z":"9","hex":"#331919","rgb":[51,25,25],"name":"Nether Brick Slab","mat_id":"91","file":"","transparent":false,"opacity":1,"texture":"44_6.png"}},"5":{"11":{"x":5,"y":"7","z":"11","hex":"#706c6c","rgb":[112,108,108],"name":"Stone Bricks","mat_id":"169","file":"","transparent":false,"opacity":1,"texture":"98_0.png"},"13":{"x":5,"y":"7","z":"13","hex":"#706c6c","rgb":[112,108,108],"name":"Stone Bricks","mat_id":"169","file":"","transparent":false,"opacity":1,"texture":"98_0.png"},"14":{"x":5,"y":"7","z":"14","hex":"#333107","rgb":[51,49,7],"name":"Nether Brick","mat_id":"186","file":"textures\/112_0.png","transparent":false,"opacity":1,"texture":"112_0.png"},"15":{"x":5,"y":"7","z":"15","hex":"#333107","rgb":[51,49,7],"name":"Nether Brick","mat_id":"186","file":"textures\/112_0.png","transparent":false,"opacity":1,"texture":"112_0.png"},"5":{"x":5,"y":"7","z":"5","hex":"#545454","rgb":[84,84,84],"name":"Smooth Double Stone Slab","mat_id":"1643","file":"","transparent":false,"opacity":1,"texture":"43_8.png"},"3":{"x":5,"y":"7","z":"3","hex":"#545454","rgb":[84,84,84],"name":"Smooth Double Stone Slab","mat_id":"1643","file":"","transparent":false,"opacity":1,"texture":"43_8.png"},"4":{"x":5,"y":"7","z":"4","hex":"#545454","rgb":[84,84,84],"name":"Smooth Double Stone Slab","mat_id":"1643","file":"","transparent":false,"opacity":1,"texture":"43_8.png"}},"4":{"7":{"x":4,"y":"7","z":"7","hex":"#545454","rgb":[84,84,84],"name":"Smooth Double Stone Slab","mat_id":"1643","file":"","transparent":false,"opacity":1,"texture":"43_8.png"},"6":{"x":4,"y":"7","z":"6","hex":"#545454","rgb":[84,84,84],"name":"Smooth Double Stone Slab","mat_id":"1643","file":"","transparent":false,"opacity":1,"texture":"43_8.png"},"14":{"x":4,"y":"7","z":"14","hex":"#545454","rgb":[84,84,84],"name":"Smooth Double Stone Slab","mat_id":"1643","file":"","transparent":false,"opacity":1,"texture":"43_8.png"},"13":{"x":4,"y":"7","z":"13","hex":"#545454","rgb":[84,84,84],"name":"Smooth Double Stone Slab","mat_id":"1643","file":"","transparent":false,"opacity":1,"texture":"43_8.png"},"8":{"x":4,"y":"7","z":"8","hex":"#545454","rgb":[84,84,84],"name":"Smooth Double Stone Slab","mat_id":"1643","file":"","transparent":false,"opacity":1,"texture":"43_8.png"}},"1":{"14":{"x":1,"y":"7","z":"14","hex":"#a4a499","rgb":[164,164,153],"name":"Stone Button (Facing East, Inactive)","mat_id":"758","file":"","transparent":false,"opacity":1,"texture":"77_1.png"},"13":{"x":1,"y":"7","z":"13","hex":"#8c8c8c","rgb":[140,140,140],"name":"Mob Head (On a Wall Facing West)","mat_id":"1426","file":"","transparent":false,"opacity":1,"texture":"144_5.png"},"12":{"x":1,"y":"7","z":"12","hex":"#a4a499","rgb":[164,164,153],"name":"Stone Button (Facing East, Inactive)","mat_id":"758","file":"","transparent":false,"opacity":1,"texture":"77_1.png"}},"3":{"10":{"x":3,"y":"7","z":"10","hex":"#545454","rgb":[84,84,84],"name":"Smooth Double Stone Slab","mat_id":"1643","file":"","transparent":false,"opacity":1,"texture":"43_8.png"},"13":{"x":3,"y":"7","z":"13","hex":"#6e6868","rgb":[110,104,104],"name":"Cobblestone Wall","mat_id":"223","file":"","transparent":false,"opacity":1,"texture":"139_0.png"},"12":{"x":3,"y":"7","z":"12","hex":"#545454","rgb":[84,84,84],"name":"Smooth Double Stone Slab","mat_id":"1643","file":"","transparent":false,"opacity":1,"texture":"43_8.png"},"11":{"x":3,"y":"7","z":"11","hex":"#545454","rgb":[84,84,84],"name":"Smooth Double Stone Slab","mat_id":"1643","file":"","transparent":false,"opacity":1,"texture":"43_8.png"},"9":{"x":3,"y":"7","z":"9","hex":"#545454","rgb":[84,84,84],"name":"Smooth Double Stone Slab","mat_id":"1643","file":"","transparent":false,"opacity":1,"texture":"43_8.png"}},"6":{"15":{"x":6,"y":"7","z":"15","hex":"#000000","rgb":[0,0,0],"name":"Anvil (South\/North)","mat_id":"326","file":"","transparent":false,"opacity":1,"texture":"145_2.png"},"14":{"x":6,"y":"7","z":"14","hex":"#6b6b6b","rgb":[107,107,107],"name":"Gray Wool","mat_id":"66","file":"textures\/35_7.png","transparent":false,"opacity":1,"texture":"35_7.png"},"1":{"x":6,"y":"7","z":"1","hex":"#545454","rgb":[84,84,84],"name":"Smooth Double Stone Slab","mat_id":"1643","file":"","transparent":false,"opacity":1,"texture":"43_8.png"},"2":{"x":6,"y":"7","z":"2","hex":"#545454","rgb":[84,84,84],"name":"Smooth Double Stone Slab","mat_id":"1643","file":"","transparent":false,"opacity":1,"texture":"43_8.png"},"3":{"x":6,"y":"7","z":"3","hex":"#545454","rgb":[84,84,84],"name":"Smooth Double Stone Slab","mat_id":"1643","file":"","transparent":false,"opacity":1,"texture":"43_8.png"},"10":{"x":6,"y":"7","z":"10","hex":"#6b6b6b","rgb":[107,107,107],"name":"Gray Wool","mat_id":"66","file":"textures\/35_7.png","transparent":false,"opacity":1,"texture":"35_7.png"},"11":{"x":6,"y":"7","z":"11","hex":"#a7a7a7","rgb":[167,167,167],"name":"Stone Brick Stairs (South, Normal)","mat_id":"482","file":"","transparent":false,"opacity":1,"texture":"109_2.png"},"12":{"x":6,"y":"7","z":"12","hex":"#000000","rgb":[0,0,0],"name":"Stone Slab (Upper)","mat_id":"493","file":"","transparent":false,"opacity":1,"texture":"44_8.png"},"13":{"x":6,"y":"7","z":"13","hex":"#6b6b6b","rgb":[107,107,107],"name":"Gray Wool","mat_id":"66","file":"textures\/35_7.png","transparent":false,"opacity":1,"texture":"35_7.png"}},"9":{"13":{"x":9,"y":"7","z":"13","hex":"#6e6868","rgb":[110,104,104],"name":"Cobblestone Wall","mat_id":"223","file":"","transparent":false,"opacity":1,"texture":"139_0.png"},"11":{"x":9,"y":"7","z":"11","hex":"#545454","rgb":[84,84,84],"name":"Smooth Double Stone Slab","mat_id":"1643","file":"","transparent":false,"opacity":1,"texture":"43_8.png"},"10":{"x":9,"y":"7","z":"10","hex":"#545454","rgb":[84,84,84],"name":"Smooth Double Stone Slab","mat_id":"1643","file":"","transparent":false,"opacity":1,"texture":"43_8.png"},"9":{"x":9,"y":"7","z":"9","hex":"#545454","rgb":[84,84,84],"name":"Smooth Double Stone Slab","mat_id":"1643","file":"","transparent":false,"opacity":1,"texture":"43_8.png"},"12":{"x":9,"y":"7","z":"12","hex":"#545454","rgb":[84,84,84],"name":"Smooth Double Stone Slab","mat_id":"1643","file":"","transparent":false,"opacity":1,"texture":"43_8.png"}},"7":{"15":{"x":7,"y":"7","z":"15","hex":"#333107","rgb":[51,49,7],"name":"Nether Brick","mat_id":"186","file":"textures\/112_0.png","transparent":false,"opacity":1,"texture":"112_0.png"},"4":{"x":7,"y":"7","z":"4","hex":"#545454","rgb":[84,84,84],"name":"Smooth Double Stone Slab","mat_id":"1643","file":"","transparent":false,"opacity":1,"texture":"43_8.png"},"14":{"x":7,"y":"7","z":"14","hex":"#333107","rgb":[51,49,7],"name":"Nether Brick","mat_id":"186","file":"textures\/112_0.png","transparent":false,"opacity":1,"texture":"112_0.png"},"11":{"x":7,"y":"7","z":"11","hex":"#706c6c","rgb":[112,108,108],"name":"Stone Bricks","mat_id":"169","file":"","transparent":false,"opacity":1,"texture":"98_0.png"},"5":{"x":7,"y":"7","z":"5","hex":"#545454","rgb":[84,84,84],"name":"Smooth Double Stone Slab","mat_id":"1643","file":"","transparent":false,"opacity":1,"texture":"43_8.png"},"3":{"x":7,"y":"7","z":"3","hex":"#545454","rgb":[84,84,84],"name":"Smooth Double Stone Slab","mat_id":"1643","file":"","transparent":false,"opacity":1,"texture":"43_8.png"}},"8":{"6":{"x":8,"y":"7","z":"6","hex":"#545454","rgb":[84,84,84],"name":"Smooth Double Stone Slab","mat_id":"1643","file":"","transparent":false,"opacity":1,"texture":"43_8.png"},"7":{"x":8,"y":"7","z":"7","hex":"#545454","rgb":[84,84,84],"name":"Smooth Double Stone Slab","mat_id":"1643","file":"","transparent":false,"opacity":1,"texture":"43_8.png"},"8":{"x":8,"y":"7","z":"8","hex":"#545454","rgb":[84,84,84],"name":"Smooth Double Stone Slab","mat_id":"1643","file":"","transparent":false,"opacity":1,"texture":"43_8.png"},"13":{"x":8,"y":"7","z":"13","hex":"#545454","rgb":[84,84,84],"name":"Smooth Double Stone Slab","mat_id":"1643","file":"","transparent":false,"opacity":1,"texture":"43_8.png"},"14":{"x":8,"y":"7","z":"14","hex":"#545454","rgb":[84,84,84],"name":"Smooth Double Stone Slab","mat_id":"1643","file":"","transparent":false,"opacity":1,"texture":"43_8.png"}},"10":{"11":{"x":10,"y":"7","z":"11","hex":"#331919","rgb":[51,25,25],"name":"Nether Brick Slab","mat_id":"91","file":"","transparent":false,"opacity":1,"texture":"44_6.png"},"10":{"x":10,"y":"7","z":"10","hex":"#331919","rgb":[51,25,25],"name":"Nether Brick Slab","mat_id":"91","file":"","transparent":false,"opacity":1,"texture":"44_6.png"},"9":{"x":10,"y":"7","z":"9","hex":"#331919","rgb":[51,25,25],"name":"Nether Brick Slab","mat_id":"91","file":"","transparent":false,"opacity":1,"texture":"44_6.png"},"17":{"x":10,"y":"7","z":"17","hex":"#333107","rgb":[51,49,7],"name":"Nether Brick","mat_id":"186","file":"textures\/112_0.png","transparent":false,"opacity":1,"texture":"112_0.png"},"16":{"x":10,"y":"7","z":"16","hex":"#333107","rgb":[51,49,7],"name":"Nether Brick","mat_id":"186","file":"textures\/112_0.png","transparent":false,"opacity":1,"texture":"112_0.png"},"15":{"x":10,"y":"7","z":"15","hex":"#333107","rgb":[51,49,7],"name":"Nether Brick","mat_id":"186","file":"textures\/112_0.png","transparent":false,"opacity":1,"texture":"112_0.png"},"14":{"x":10,"y":"7","z":"14","hex":"#6b6b6b","rgb":[107,107,107],"name":"Gray Wool","mat_id":"66","file":"textures\/35_7.png","transparent":false,"opacity":1,"texture":"35_7.png"},"13":{"x":10,"y":"7","z":"13","hex":"#333107","rgb":[51,49,7],"name":"Nether Brick","mat_id":"186","file":"textures\/112_0.png","transparent":false,"opacity":1,"texture":"112_0.png"},"12":{"x":10,"y":"7","z":"12","hex":"#6b6b6b","rgb":[107,107,107],"name":"Gray Wool","mat_id":"66","file":"textures\/35_7.png","transparent":false,"opacity":1,"texture":"35_7.png"}},"11":{"12":{"x":11,"y":"7","z":"12","hex":"#a4a499","rgb":[164,164,153],"name":"Stone Button (Facing West, Inactive)","mat_id":"759","file":"","transparent":false,"opacity":1,"texture":"77_2.png"},"13":{"x":11,"y":"7","z":"13","hex":"#8c8c8c","rgb":[140,140,140],"name":"Mob Head (On a Wall Facing East)","mat_id":"1425","file":"","transparent":false,"opacity":1,"texture":"144_4.png"},"14":{"x":11,"y":"7","z":"14","hex":"#a4a499","rgb":[164,164,153],"name":"Stone Button (Facing West, Inactive)","mat_id":"759","file":"","transparent":false,"opacity":1,"texture":"77_2.png"}}},"8":{"8":{"11":{"x":8,"y":"8","z":"11","hex":"#400000","rgb":[64,0,0],"name":"Nether Brick Stairs (East, Normal)","mat_id":"188","file":"","transparent":false,"opacity":1,"texture":"114_0.png"},"7":{"x":8,"y":"8","z":"7","hex":"#666363","rgb":[102,99,99],"name":"Stone Slab","mat_id":"85","file":"","transparent":false,"opacity":1,"texture":"44_0.png"},"8":{"x":8,"y":"8","z":"8","hex":"#666363","rgb":[102,99,99],"name":"Stone Slab","mat_id":"85","file":"","transparent":false,"opacity":1,"texture":"44_0.png"},"10":{"x":8,"y":"8","z":"10","hex":"#400000","rgb":[64,0,0],"name":"Nether Brick Stairs (East, Normal)","mat_id":"188","file":"","transparent":false,"opacity":1,"texture":"114_0.png"},"9":{"x":8,"y":"8","z":"9","hex":"#666363","rgb":[102,99,99],"name":"Stone Slab","mat_id":"85","file":"","transparent":false,"opacity":1,"texture":"44_0.png"},"12":{"x":8,"y":"8","z":"12","hex":"#400000","rgb":[64,0,0],"name":"Nether Brick Stairs (East, Normal)","mat_id":"188","file":"","transparent":false,"opacity":1,"texture":"114_0.png"},"13":{"x":8,"y":"8","z":"13","hex":"#666363","rgb":[102,99,99],"name":"Stone Slab","mat_id":"85","file":"","transparent":false,"opacity":1,"texture":"44_0.png"}},"5":{"12":{"x":5,"y":"8","z":"12","hex":"#666363","rgb":[102,99,99],"name":"Stone Brick Stairs (East)","mat_id":"183","file":"","transparent":false,"opacity":1,"texture":"109_0.png"},"13":{"x":5,"y":"8","z":"13","hex":"#706c6c","rgb":[112,108,108],"name":"Stone Bricks","mat_id":"169","file":"","transparent":false,"opacity":1,"texture":"98_0.png"},"14":{"x":5,"y":"8","z":"14","hex":"#333107","rgb":[51,49,7],"name":"Nether Brick","mat_id":"186","file":"textures\/112_0.png","transparent":false,"opacity":1,"texture":"112_0.png"},"11":{"x":5,"y":"8","z":"11","hex":"#666363","rgb":[102,99,99],"name":"Stone Brick Stairs (East)","mat_id":"183","file":"","transparent":false,"opacity":1,"texture":"109_0.png"},"10":{"x":5,"y":"8","z":"10","hex":"#a7a7a7","rgb":[167,167,167],"name":"Stone Brick Stairs (South, Normal)","mat_id":"482","file":"","transparent":false,"opacity":1,"texture":"109_2.png"},"9":{"x":5,"y":"8","z":"9","hex":"#333107","rgb":[51,49,7],"name":"Nether Brick","mat_id":"186","file":"textures\/112_0.png","transparent":false,"opacity":1,"texture":"112_0.png"},"8":{"x":5,"y":"8","z":"8","hex":"#333107","rgb":[51,49,7],"name":"Nether Brick","mat_id":"186","file":"textures\/112_0.png","transparent":false,"opacity":1,"texture":"112_0.png"},"7":{"x":5,"y":"8","z":"7","hex":"#331919","rgb":[51,25,25],"name":"Nether Brick Slab","mat_id":"91","file":"","transparent":false,"opacity":1,"texture":"44_6.png"},"6":{"x":5,"y":"8","z":"6","hex":"#331919","rgb":[51,25,25],"name":"Nether Brick Slab","mat_id":"91","file":"","transparent":false,"opacity":1,"texture":"44_6.png"},"5":{"x":5,"y":"8","z":"5","hex":"#331919","rgb":[51,25,25],"name":"Nether Brick Slab","mat_id":"91","file":"","transparent":false,"opacity":1,"texture":"44_6.png"},"15":{"x":5,"y":"8","z":"15","hex":"#333107","rgb":[51,49,7],"name":"Nether Brick","mat_id":"186","file":"textures\/112_0.png","transparent":false,"opacity":1,"texture":"112_0.png"},"18":{"x":5,"y":"8","z":"18","hex":"#a2e098","rgb":[162,224,152],"name":"Lime Stained Glass Pane","mat_id":"265","file":"","transparent":true,"opacity":0.5,"texture":"160_5.png"}},"9":{"11":{"x":9,"y":"8","z":"11","hex":"#666363","rgb":[102,99,99],"name":"Stone Slab","mat_id":"85","file":"","transparent":false,"opacity":1,"texture":"44_0.png"},"10":{"x":9,"y":"8","z":"10","hex":"#666363","rgb":[102,99,99],"name":"Stone Slab","mat_id":"85","file":"","transparent":false,"opacity":1,"texture":"44_0.png"}},"3":{"10":{"x":3,"y":"8","z":"10","hex":"#666363","rgb":[102,99,99],"name":"Stone Slab","mat_id":"85","file":"","transparent":false,"opacity":1,"texture":"44_0.png"},"11":{"x":3,"y":"8","z":"11","hex":"#666363","rgb":[102,99,99],"name":"Stone Slab","mat_id":"85","file":"","transparent":false,"opacity":1,"texture":"44_0.png"}},"4":{"7":{"x":4,"y":"8","z":"7","hex":"#666363","rgb":[102,99,99],"name":"Stone Slab","mat_id":"85","file":"","transparent":false,"opacity":1,"texture":"44_0.png"},"8":{"x":4,"y":"8","z":"8","hex":"#666363","rgb":[102,99,99],"name":"Stone Slab","mat_id":"85","file":"","transparent":false,"opacity":1,"texture":"44_0.png"},"9":{"x":4,"y":"8","z":"9","hex":"#666363","rgb":[102,99,99],"name":"Stone Slab","mat_id":"85","file":"","transparent":false,"opacity":1,"texture":"44_0.png"},"10":{"x":4,"y":"8","z":"10","hex":"#400000","rgb":[64,0,0],"name":"Nether Brick Stairs (West, Normal)","mat_id":"601","file":"","transparent":false,"opacity":1,"texture":"114_1.png"},"11":{"x":4,"y":"8","z":"11","hex":"#400000","rgb":[64,0,0],"name":"Nether Brick Stairs (West, Normal)","mat_id":"601","file":"","transparent":false,"opacity":1,"texture":"114_1.png"},"12":{"x":4,"y":"8","z":"12","hex":"#400000","rgb":[64,0,0],"name":"Nether Brick Stairs (West, Normal)","mat_id":"601","file":"","transparent":false,"opacity":1,"texture":"114_1.png"},"13":{"x":4,"y":"8","z":"13","hex":"#666363","rgb":[102,99,99],"name":"Stone Slab","mat_id":"85","file":"","transparent":false,"opacity":1,"texture":"44_0.png"}},"10":{"9":{"x":10,"y":"8","z":"9","hex":"#331919","rgb":[51,25,25],"name":"Nether Brick Slab","mat_id":"91","file":"","transparent":false,"opacity":1,"texture":"44_6.png"},"10":{"x":10,"y":"8","z":"10","hex":"#331919","rgb":[51,25,25],"name":"Nether Brick Slab","mat_id":"91","file":"","transparent":false,"opacity":1,"texture":"44_6.png"},"13":{"x":10,"y":"8","z":"13","hex":"#6b6b6b","rgb":[107,107,107],"name":"Gray Wool","mat_id":"66","file":"textures\/35_7.png","transparent":false,"opacity":1,"texture":"35_7.png"},"11":{"x":10,"y":"8","z":"11","hex":"#331919","rgb":[51,25,25],"name":"Nether Brick Slab","mat_id":"91","file":"","transparent":false,"opacity":1,"texture":"44_6.png"},"12":{"x":10,"y":"8","z":"12","hex":"#6b6b6b","rgb":[107,107,107],"name":"Gray Wool","mat_id":"66","file":"textures\/35_7.png","transparent":false,"opacity":1,"texture":"35_7.png"},"14":{"x":10,"y":"8","z":"14","hex":"#6b6b6b","rgb":[107,107,107],"name":"Gray Wool","mat_id":"66","file":"textures\/35_7.png","transparent":false,"opacity":1,"texture":"35_7.png"},"15":{"x":10,"y":"8","z":"15","hex":"#400000","rgb":[64,0,0],"name":"Nether Brick Stairs (South, Normal)","mat_id":"602","file":"","transparent":false,"opacity":1,"texture":"114_2.png"},"16":{"x":10,"y":"8","z":"16","hex":"#331919","rgb":[51,25,25],"name":"Nether Brick Slab","mat_id":"91","file":"","transparent":false,"opacity":1,"texture":"44_6.png"}},"1":{"14":{"x":1,"y":"8","z":"14","hex":"#591b1b","rgb":[89,27,27],"name":"Nether Brick Fence","mat_id":"187","file":"","transparent":false,"opacity":1,"texture":"113_0.png"},"13":{"x":1,"y":"8","z":"13","hex":"#a4a499","rgb":[164,164,153],"name":"Stone Button (Facing East, Inactive)","mat_id":"758","file":"","transparent":false,"opacity":1,"texture":"77_1.png"}},"6":{"4":{"x":6,"y":"8","z":"4","hex":"#666363","rgb":[102,99,99],"name":"Stone Slab","mat_id":"85","file":"","transparent":false,"opacity":1,"texture":"44_0.png"},"5":{"x":6,"y":"8","z":"5","hex":"#666363","rgb":[102,99,99],"name":"Stone Slab","mat_id":"85","file":"","transparent":false,"opacity":1,"texture":"44_0.png"},"6":{"x":6,"y":"8","z":"6","hex":"#545454","rgb":[84,84,84],"name":"Smooth Double Stone Slab","mat_id":"1643","file":"","transparent":false,"opacity":1,"texture":"43_8.png"},"8":{"x":6,"y":"8","z":"8","hex":"#545454","rgb":[84,84,84],"name":"Smooth Double Stone Slab","mat_id":"1643","file":"","transparent":false,"opacity":1,"texture":"43_8.png"},"9":{"x":6,"y":"8","z":"9","hex":"#6b6b6b","rgb":[107,107,107],"name":"Gray Wool","mat_id":"66","file":"textures\/35_7.png","transparent":false,"opacity":1,"texture":"35_7.png"},"10":{"x":6,"y":"8","z":"10","hex":"#6b6b6b","rgb":[107,107,107],"name":"Gray Wool","mat_id":"66","file":"textures\/35_7.png","transparent":false,"opacity":1,"texture":"35_7.png"},"11":{"x":6,"y":"8","z":"11","hex":"#919191","rgb":[145,145,145],"name":"Lever (On Block Side Facing North, Not Active)","mat_id":"386","file":"","transparent":false,"opacity":1,"texture":"69_4.png"},"12":{"x":6,"y":"8","z":"12","hex":"#8d8b8b","rgb":[141,139,139],"name":"Wall-Mounted Banner (west-southwest)","mat_id":"368","file":"","transparent":false,"opacity":1,"texture":"177_3.png"},"3":{"x":6,"y":"8","z":"3","hex":"#666363","rgb":[102,99,99],"name":"Stone Slab","mat_id":"85","file":"","transparent":false,"opacity":1,"texture":"44_0.png"},"7":{"x":6,"y":"8","z":"7","hex":"#545454","rgb":[84,84,84],"name":"Smooth Double Stone Slab","mat_id":"1643","file":"","transparent":false,"opacity":1,"texture":"43_8.png"},"13":{"x":6,"y":"8","z":"13","hex":"#6b6b6b","rgb":[107,107,107],"name":"Gray Wool","mat_id":"66","file":"textures\/35_7.png","transparent":false,"opacity":1,"texture":"35_7.png"},"14":{"x":6,"y":"8","z":"14","hex":"#6b6b6b","rgb":[107,107,107],"name":"Gray Wool","mat_id":"66","file":"textures\/35_7.png","transparent":false,"opacity":1,"texture":"35_7.png"},"18":{"x":6,"y":"8","z":"18","hex":"#c1ed9e","rgb":[193,237,158],"name":"Lime Stained Glass","mat_id":"151","file":"","transparent":true,"opacity":0.5,"texture":"95_5.png"},"17":{"x":6,"y":"8","z":"17","hex":"#c1ed9e","rgb":[193,237,158],"name":"Lime Stained Glass","mat_id":"151","file":"","transparent":true,"opacity":0.5,"texture":"95_5.png"},"16":{"x":6,"y":"8","z":"16","hex":"#6b6b6b","rgb":[107,107,107],"name":"Gray Wool","mat_id":"66","file":"textures\/35_7.png","transparent":false,"opacity":1,"texture":"35_7.png"},"20":{"x":6,"y":"8","z":"20","hex":"#a2e098","rgb":[162,224,152],"name":"Lime Stained Glass Pane","mat_id":"265","file":"","transparent":true,"opacity":0.5,"texture":"160_5.png"},"15":{"x":6,"y":"8","z":"15","hex":"#6b6b6b","rgb":[107,107,107],"name":"Gray Wool","mat_id":"66","file":"textures\/35_7.png","transparent":false,"opacity":1,"texture":"35_7.png"},"19":{"x":6,"y":"8","z":"19","hex":"#a2e098","rgb":[162,224,152],"name":"Lime Stained Glass Pane","mat_id":"265","file":"","transparent":true,"opacity":0.5,"texture":"160_5.png"}},"2":{"15":{"x":2,"y":"8","z":"15","hex":"#400000","rgb":[64,0,0],"name":"Nether Brick Stairs (South, Normal)","mat_id":"602","file":"","transparent":false,"opacity":1,"texture":"114_2.png"},"11":{"x":2,"y":"8","z":"11","hex":"#331919","rgb":[51,25,25],"name":"Nether Brick Slab","mat_id":"91","file":"","transparent":false,"opacity":1,"texture":"44_6.png"},"10":{"x":2,"y":"8","z":"10","hex":"#331919","rgb":[51,25,25],"name":"Nether Brick Slab","mat_id":"91","file":"","transparent":false,"opacity":1,"texture":"44_6.png"},"9":{"x":2,"y":"8","z":"9","hex":"#331919","rgb":[51,25,25],"name":"Nether Brick Slab","mat_id":"91","file":"","transparent":false,"opacity":1,"texture":"44_6.png"},"12":{"x":2,"y":"8","z":"12","hex":"#6b6b6b","rgb":[107,107,107],"name":"Gray Wool","mat_id":"66","file":"textures\/35_7.png","transparent":false,"opacity":1,"texture":"35_7.png"},"13":{"x":2,"y":"8","z":"13","hex":"#6b6b6b","rgb":[107,107,107],"name":"Gray Wool","mat_id":"66","file":"textures\/35_7.png","transparent":false,"opacity":1,"texture":"35_7.png"},"16":{"x":2,"y":"8","z":"16","hex":"#331919","rgb":[51,25,25],"name":"Nether Brick Slab","mat_id":"91","file":"","transparent":false,"opacity":1,"texture":"44_6.png"},"14":{"x":2,"y":"8","z":"14","hex":"#6b6b6b","rgb":[107,107,107],"name":"Gray Wool","mat_id":"66","file":"textures\/35_7.png","transparent":false,"opacity":1,"texture":"35_7.png"}},"7":{"11":{"x":7,"y":"8","z":"11","hex":"#666363","rgb":[102,99,99],"name":"Stone Brick Stairs (West)","mat_id":"351","file":"","transparent":false,"opacity":1,"texture":"109_1.png"},"12":{"x":7,"y":"8","z":"12","hex":"#666363","rgb":[102,99,99],"name":"Stone Brick Stairs (West)","mat_id":"351","file":"","transparent":false,"opacity":1,"texture":"109_1.png"},"18":{"x":7,"y":"8","z":"18","hex":"#a2e098","rgb":[162,224,152],"name":"Lime Stained Glass Pane","mat_id":"265","file":"","transparent":true,"opacity":0.5,"texture":"160_5.png"},"17":{"x":7,"y":"8","z":"17","hex":"#a2e098","rgb":[162,224,152],"name":"Lime Stained Glass Pane","mat_id":"265","file":"","transparent":true,"opacity":0.5,"texture":"160_5.png"},"15":{"x":7,"y":"8","z":"15","hex":"#333107","rgb":[51,49,7],"name":"Nether Brick","mat_id":"186","file":"textures\/112_0.png","transparent":false,"opacity":1,"texture":"112_0.png"},"14":{"x":7,"y":"8","z":"14","hex":"#333107","rgb":[51,49,7],"name":"Nether Brick","mat_id":"186","file":"textures\/112_0.png","transparent":false,"opacity":1,"texture":"112_0.png"},"13":{"x":7,"y":"8","z":"13","hex":"#706c6c","rgb":[112,108,108],"name":"Stone Bricks","mat_id":"169","file":"","transparent":false,"opacity":1,"texture":"98_0.png"},"10":{"x":7,"y":"8","z":"10","hex":"#a7a7a7","rgb":[167,167,167],"name":"Stone Brick Stairs (South, Normal)","mat_id":"482","file":"","transparent":false,"opacity":1,"texture":"109_2.png"},"9":{"x":7,"y":"8","z":"9","hex":"#333107","rgb":[51,49,7],"name":"Nether Brick","mat_id":"186","file":"textures\/112_0.png","transparent":false,"opacity":1,"texture":"112_0.png"},"8":{"x":7,"y":"8","z":"8","hex":"#333107","rgb":[51,49,7],"name":"Nether Brick","mat_id":"186","file":"textures\/112_0.png","transparent":false,"opacity":1,"texture":"112_0.png"},"7":{"x":7,"y":"8","z":"7","hex":"#331919","rgb":[51,25,25],"name":"Nether Brick Slab","mat_id":"91","file":"","transparent":false,"opacity":1,"texture":"44_6.png"},"6":{"x":7,"y":"8","z":"6","hex":"#331919","rgb":[51,25,25],"name":"Nether Brick Slab","mat_id":"91","file":"","transparent":false,"opacity":1,"texture":"44_6.png"},"5":{"x":7,"y":"8","z":"5","hex":"#331919","rgb":[51,25,25],"name":"Nether Brick Slab","mat_id":"91","file":"","transparent":false,"opacity":1,"texture":"44_6.png"}},"11":{"13":{"x":11,"y":"8","z":"13","hex":"#a4a499","rgb":[164,164,153],"name":"Stone Button (Facing West, Inactive)","mat_id":"759","file":"","transparent":false,"opacity":1,"texture":"77_2.png"},"14":{"x":11,"y":"8","z":"14","hex":"#591b1b","rgb":[89,27,27],"name":"Nether Brick Fence","mat_id":"187","file":"","transparent":false,"opacity":1,"texture":"113_0.png"}}},"9":{"1":{"14":{"x":1,"y":"9","z":"14","hex":"#591b1b","rgb":[89,27,27],"name":"Nether Brick Fence","mat_id":"187","file":"","transparent":false,"opacity":1,"texture":"113_0.png"}},"10":{"14":{"x":10,"y":"9","z":"14","hex":"#706c6c","rgb":[112,108,108],"name":"Stone Bricks","mat_id":"169","file":"","transparent":false,"opacity":1,"texture":"98_0.png"},"13":{"x":10,"y":"9","z":"13","hex":"#706c6c","rgb":[112,108,108],"name":"Stone Bricks","mat_id":"169","file":"","transparent":false,"opacity":1,"texture":"98_0.png"},"15":{"x":10,"y":"9","z":"15","hex":"#706c6c","rgb":[112,108,108],"name":"Stone Bricks","mat_id":"169","file":"","transparent":false,"opacity":1,"texture":"98_0.png"}},"11":{"14":{"x":11,"y":"9","z":"14","hex":"#591b1b","rgb":[89,27,27],"name":"Nether Brick Fence","mat_id":"187","file":"","transparent":false,"opacity":1,"texture":"113_0.png"}},"2":{"15":{"x":2,"y":"9","z":"15","hex":"#706c6c","rgb":[112,108,108],"name":"Stone Bricks","mat_id":"169","file":"","transparent":false,"opacity":1,"texture":"98_0.png"},"14":{"x":2,"y":"9","z":"14","hex":"#706c6c","rgb":[112,108,108],"name":"Stone Bricks","mat_id":"169","file":"","transparent":false,"opacity":1,"texture":"98_0.png"},"13":{"x":2,"y":"9","z":"13","hex":"#706c6c","rgb":[112,108,108],"name":"Stone Bricks","mat_id":"169","file":"","transparent":false,"opacity":1,"texture":"98_0.png"}},"6":{"15":{"x":6,"y":"9","z":"15","hex":"#400000","rgb":[64,0,0],"name":"Nether Brick Stairs (North, Normal)","mat_id":"603","file":"","transparent":false,"opacity":1,"texture":"114_3.png"},"10":{"x":6,"y":"9","z":"10","hex":"#706a6a","rgb":[112,106,106],"name":"Black Stained Glass","mat_id":"161","file":"","transparent":true,"opacity":0.5,"texture":"95_15.png"},"12":{"x":6,"y":"9","z":"12","hex":"#71574a","rgb":[113,87,74],"name":"Wooden Button (Facing South, Inactive)","mat_id":"305","file":"","transparent":false,"opacity":1,"texture":"143_3.png"},"13":{"x":6,"y":"9","z":"13","hex":"#400000","rgb":[64,0,0],"name":"Nether Brick Stairs (South, Normal)","mat_id":"602","file":"","transparent":false,"opacity":1,"texture":"114_2.png"},"14":{"x":6,"y":"9","z":"14","hex":"#3aa830","rgb":[58,168,48],"name":"Green Wool","mat_id":"71","file":"textures\/35_13.png","transparent":false,"opacity":1,"texture":"35_13.png"},"9":{"x":6,"y":"9","z":"9","hex":"#706a6a","rgb":[112,106,106],"name":"Black Stained Glass","mat_id":"161","file":"","transparent":true,"opacity":0.5,"texture":"95_15.png"}},"5":{"15":{"x":5,"y":"9","z":"15","hex":"#333107","rgb":[51,49,7],"name":"Nether Brick","mat_id":"186","file":"textures\/112_0.png","transparent":false,"opacity":1,"texture":"112_0.png"},"14":{"x":5,"y":"9","z":"14","hex":"#333107","rgb":[51,49,7],"name":"Nether Brick","mat_id":"186","file":"textures\/112_0.png","transparent":false,"opacity":1,"texture":"112_0.png"},"13":{"x":5,"y":"9","z":"13","hex":"#333107","rgb":[51,49,7],"name":"Nether Brick","mat_id":"186","file":"textures\/112_0.png","transparent":false,"opacity":1,"texture":"112_0.png"},"12":{"x":5,"y":"9","z":"12","hex":"#333107","rgb":[51,49,7],"name":"Nether Brick","mat_id":"186","file":"textures\/112_0.png","transparent":false,"opacity":1,"texture":"112_0.png"},"11":{"x":5,"y":"9","z":"11","hex":"#706a6a","rgb":[112,106,106],"name":"Black Stained Glass","mat_id":"161","file":"","transparent":true,"opacity":0.5,"texture":"95_15.png"},"10":{"x":5,"y":"9","z":"10","hex":"#706a6a","rgb":[112,106,106],"name":"Black Stained Glass","mat_id":"161","file":"","transparent":true,"opacity":0.5,"texture":"95_15.png"},"16":{"x":5,"y":"9","z":"16","hex":"#000000","rgb":[0,0,0],"name":"Stone Brick Slab (Upper)","mat_id":"498","file":"","transparent":false,"opacity":1,"texture":"44_13.png"}},"8":{"13":{"x":8,"y":"9","z":"13","hex":"#666363","rgb":[102,99,99],"name":"Stone Brick Stairs (East)","mat_id":"183","file":"","transparent":false,"opacity":1,"texture":"109_0.png"},"14":{"x":8,"y":"9","z":"14","hex":"#666363","rgb":[102,99,99],"name":"Stone Brick Stairs (East)","mat_id":"183","file":"","transparent":false,"opacity":1,"texture":"109_0.png"},"15":{"x":8,"y":"9","z":"15","hex":"#666363","rgb":[102,99,99],"name":"Stone Brick Stairs (East)","mat_id":"183","file":"","transparent":false,"opacity":1,"texture":"109_0.png"}},"7":{"11":{"x":7,"y":"9","z":"11","hex":"#706a6a","rgb":[112,106,106],"name":"Black Stained Glass","mat_id":"161","file":"","transparent":true,"opacity":0.5,"texture":"95_15.png"},"10":{"x":7,"y":"9","z":"10","hex":"#706a6a","rgb":[112,106,106],"name":"Black Stained Glass","mat_id":"161","file":"","transparent":true,"opacity":0.5,"texture":"95_15.png"},"16":{"x":7,"y":"9","z":"16","hex":"#000000","rgb":[0,0,0],"name":"Stone Brick Slab (Upper)","mat_id":"498","file":"","transparent":false,"opacity":1,"texture":"44_13.png"},"15":{"x":7,"y":"9","z":"15","hex":"#333107","rgb":[51,49,7],"name":"Nether Brick","mat_id":"186","file":"textures\/112_0.png","transparent":false,"opacity":1,"texture":"112_0.png"},"14":{"x":7,"y":"9","z":"14","hex":"#333107","rgb":[51,49,7],"name":"Nether Brick","mat_id":"186","file":"textures\/112_0.png","transparent":false,"opacity":1,"texture":"112_0.png"},"12":{"x":7,"y":"9","z":"12","hex":"#333107","rgb":[51,49,7],"name":"Nether Brick","mat_id":"186","file":"textures\/112_0.png","transparent":false,"opacity":1,"texture":"112_0.png"},"13":{"x":7,"y":"9","z":"13","hex":"#333107","rgb":[51,49,7],"name":"Nether Brick","mat_id":"186","file":"textures\/112_0.png","transparent":false,"opacity":1,"texture":"112_0.png"}},"4":{"15":{"x":4,"y":"9","z":"15","hex":"#666363","rgb":[102,99,99],"name":"Stone Brick Stairs (West)","mat_id":"351","file":"","transparent":false,"opacity":1,"texture":"109_1.png"},"14":{"x":4,"y":"9","z":"14","hex":"#666363","rgb":[102,99,99],"name":"Stone Brick Stairs (West)","mat_id":"351","file":"","transparent":false,"opacity":1,"texture":"109_1.png"},"13":{"x":4,"y":"9","z":"13","hex":"#666363","rgb":[102,99,99],"name":"Stone Brick Stairs (West)","mat_id":"351","file":"","transparent":false,"opacity":1,"texture":"109_1.png"}}},"10":{"7":{"13":{"x":7,"y":"10","z":"13","hex":"#666363","rgb":[102,99,99],"name":"Stone Brick Stairs (East)","mat_id":"183","file":"","transparent":false,"opacity":1,"texture":"109_0.png"},"12":{"x":7,"y":"10","z":"12","hex":"#71574a","rgb":[113,87,74],"name":"Wooden Button (Facing Up, Inactive)","mat_id":"396","file":"","transparent":false,"opacity":1,"texture":"143_5.png"},"16":{"x":7,"y":"10","z":"16","hex":"#666363","rgb":[102,99,99],"name":"Stone Brick Stairs (East)","mat_id":"183","file":"","transparent":false,"opacity":1,"texture":"109_0.png"},"15":{"x":7,"y":"10","z":"15","hex":"#666363","rgb":[102,99,99],"name":"Stone Brick Stairs (East)","mat_id":"183","file":"","transparent":false,"opacity":1,"texture":"109_0.png"},"14":{"x":7,"y":"10","z":"14","hex":"#666363","rgb":[102,99,99],"name":"Stone Brick Stairs (East)","mat_id":"183","file":"","transparent":false,"opacity":1,"texture":"109_0.png"}},"2":{"13":{"x":2,"y":"10","z":"13","hex":"#706c6c","rgb":[112,108,108],"name":"Stone Bricks","mat_id":"169","file":"","transparent":false,"opacity":1,"texture":"98_0.png"},"15":{"x":2,"y":"10","z":"15","hex":"#706c6c","rgb":[112,108,108],"name":"Stone Bricks","mat_id":"169","file":"","transparent":false,"opacity":1,"texture":"98_0.png"},"14":{"x":2,"y":"10","z":"14","hex":"#706c6c","rgb":[112,108,108],"name":"Stone Bricks","mat_id":"169","file":"","transparent":false,"opacity":1,"texture":"98_0.png"}},"6":{"11":{"x":6,"y":"10","z":"11","hex":"#331919","rgb":[51,25,25],"name":"Nether Brick Slab","mat_id":"91","file":"","transparent":false,"opacity":1,"texture":"44_6.png"},"15":{"x":6,"y":"10","z":"15","hex":"#a4a499","rgb":[164,164,153],"name":"Stone Button (Facing North, Inactive)","mat_id":"308","file":"","transparent":false,"opacity":1,"texture":"77_4.png"},"14":{"x":6,"y":"10","z":"14","hex":"#b3adad","rgb":[179,173,173],"name":"Quartz Block","mat_id":"225","file":"textures\/155_0.png","transparent":false,"opacity":1,"texture":"155_0.png"},"12":{"x":6,"y":"10","z":"12","hex":"#553c2d","rgb":[85,60,45],"name":"Wooden Trapdoor (South from block, Closed, Bottom half)","mat_id":"866","file":"","transparent":false,"opacity":1,"texture":"96_1.png"}},"10":{"14":{"x":10,"y":"10","z":"14","hex":"#706c6c","rgb":[112,108,108],"name":"Stone Bricks","mat_id":"169","file":"","transparent":false,"opacity":1,"texture":"98_0.png"},"13":{"x":10,"y":"10","z":"13","hex":"#706c6c","rgb":[112,108,108],"name":"Stone Bricks","mat_id":"169","file":"","transparent":false,"opacity":1,"texture":"98_0.png"},"15":{"x":10,"y":"10","z":"15","hex":"#706c6c","rgb":[112,108,108],"name":"Stone Bricks","mat_id":"169","file":"","transparent":false,"opacity":1,"texture":"98_0.png"}},"5":{"16":{"x":5,"y":"10","z":"16","hex":"#666363","rgb":[102,99,99],"name":"Stone Brick Stairs (West)","mat_id":"351","file":"","transparent":false,"opacity":1,"texture":"109_1.png"},"14":{"x":5,"y":"10","z":"14","hex":"#666363","rgb":[102,99,99],"name":"Stone Brick Stairs (West)","mat_id":"351","file":"","transparent":false,"opacity":1,"texture":"109_1.png"},"13":{"x":5,"y":"10","z":"13","hex":"#666363","rgb":[102,99,99],"name":"Stone Brick Stairs (West)","mat_id":"351","file":"","transparent":false,"opacity":1,"texture":"109_1.png"},"15":{"x":5,"y":"10","z":"15","hex":"#666363","rgb":[102,99,99],"name":"Stone Brick Stairs (West)","mat_id":"351","file":"","transparent":false,"opacity":1,"texture":"109_1.png"}}},"11":{"10":{"14":{"x":10,"y":"11","z":"14","hex":"#706c6c","rgb":[112,108,108],"name":"Stone Bricks","mat_id":"169","file":"","transparent":false,"opacity":1,"texture":"98_0.png"},"13":{"x":10,"y":"11","z":"13","hex":"#706c6c","rgb":[112,108,108],"name":"Stone Bricks","mat_id":"169","file":"","transparent":false,"opacity":1,"texture":"98_0.png"},"15":{"x":10,"y":"11","z":"15","hex":"#a7a7a7","rgb":[167,167,167],"name":"Stone Brick Stairs (South, Normal)","mat_id":"482","file":"","transparent":false,"opacity":1,"texture":"109_2.png"}},"2":{"13":{"x":2,"y":"11","z":"13","hex":"#706c6c","rgb":[112,108,108],"name":"Stone Bricks","mat_id":"169","file":"","transparent":false,"opacity":1,"texture":"98_0.png"},"15":{"x":2,"y":"11","z":"15","hex":"#a7a7a7","rgb":[167,167,167],"name":"Stone Brick Stairs (South, Normal)","mat_id":"482","file":"","transparent":false,"opacity":1,"texture":"109_2.png"},"14":{"x":2,"y":"11","z":"14","hex":"#706c6c","rgb":[112,108,108],"name":"Stone Bricks","mat_id":"169","file":"","transparent":false,"opacity":1,"texture":"98_0.png"}},"6":{"14":{"x":6,"y":"11","z":"14","hex":"#123d03","rgb":[18,61,3],"name":"Green Carpet","mat_id":"1109","file":"","transparent":false,"opacity":1,"texture":"171_13.png"}}},"12":{"10":{"13":{"x":10,"y":"12","z":"13","hex":"#706c6c","rgb":[112,108,108],"name":"Stone Bricks","mat_id":"169","file":"","transparent":false,"opacity":1,"texture":"98_0.png"},"14":{"x":10,"y":"12","z":"14","hex":"#706c6c","rgb":[112,108,108],"name":"Stone Bricks","mat_id":"169","file":"","transparent":false,"opacity":1,"texture":"98_0.png"}},"2":{"13":{"x":2,"y":"12","z":"13","hex":"#706c6c","rgb":[112,108,108],"name":"Stone Bricks","mat_id":"169","file":"","transparent":false,"opacity":1,"texture":"98_0.png"},"14":{"x":2,"y":"12","z":"14","hex":"#706c6c","rgb":[112,108,108],"name":"Stone Bricks","mat_id":"169","file":"","transparent":false,"opacity":1,"texture":"98_0.png"}}},"13":{"10":{"14":{"x":10,"y":"13","z":"14","hex":"#a7a7a7","rgb":[167,167,167],"name":"Stone Brick Stairs (South, Normal)","mat_id":"482","file":"","transparent":false,"opacity":1,"texture":"109_2.png"},"13":{"x":10,"y":"13","z":"13","hex":"#706c6c","rgb":[112,108,108],"name":"Stone Bricks","mat_id":"169","file":"","transparent":false,"opacity":1,"texture":"98_0.png"}},"2":{"13":{"x":2,"y":"13","z":"13","hex":"#706c6c","rgb":[112,108,108],"name":"Stone Bricks","mat_id":"169","file":"","transparent":false,"opacity":1,"texture":"98_0.png"}}}}