{"1":{"3":{"3":{"x":3,"y":"1","z":"3","hex":"#dbdbdb","rgb":[219,219,219],"name":"Snow Block","mat_id":"128","file":"textures\/80_0.png","transparent":false,"opacity":1,"texture":"80_0.png"}}},"2":{"3":{"4":{"x":3,"y":"2","z":"4","hex":"#82b3b3","rgb":[130,179,179],"name":"Packed Ice","mat_id":"1652","file":"","transparent":false,"opacity":1,"texture":"174_0.png"},"3":{"x":3,"y":"2","z":"3","hex":"#dbdbdb","rgb":[219,219,219],"name":"Snow Block","mat_id":"128","file":"textures\/80_0.png","transparent":false,"opacity":1,"texture":"80_0.png"},"2":{"x":3,"y":"2","z":"2","hex":"#82b3b3","rgb":[130,179,179],"name":"Packed Ice","mat_id":"1652","file":"","transparent":false,"opacity":1,"texture":"174_0.png"}},"4":{"3":{"x":4,"y":"2","z":"3","hex":"#82b3b3","rgb":[130,179,179],"name":"Packed Ice","mat_id":"1652","file":"","transparent":false,"opacity":1,"texture":"174_0.png"}},"2":{"3":{"x":2,"y":"2","z":"3","hex":"#82b3b3","rgb":[130,179,179],"name":"Packed Ice","mat_id":"1652","file":"","transparent":false,"opacity":1,"texture":"174_0.png"}}},"3":{"5":{"2":{"x":5,"y":"3","z":"2","hex":"#82b3b3","rgb":[130,179,179],"name":"Packed Ice","mat_id":"1652","file":"","transparent":false,"opacity":1,"texture":"174_0.png"},"3":{"x":5,"y":"3","z":"3","hex":"#82b3b3","rgb":[130,179,179],"name":"Packed Ice","mat_id":"1652","file":"","transparent":false,"opacity":1,"texture":"174_0.png"},"4":{"x":5,"y":"3","z":"4","hex":"#82b3b3","rgb":[130,179,179],"name":"Packed Ice","mat_id":"1652","file":"","transparent":false,"opacity":1,"texture":"174_0.png"}},"3":{"4":{"x":3,"y":"3","z":"4","hex":"#82b3b3","rgb":[130,179,179],"name":"Packed Ice","mat_id":"1652","file":"","transparent":false,"opacity":1,"texture":"174_0.png"},"5":{"x":3,"y":"3","z":"5","hex":"#82b3b3","rgb":[130,179,179],"name":"Packed Ice","mat_id":"1652","file":"","transparent":false,"opacity":1,"texture":"174_0.png"},"3":{"x":3,"y":"3","z":"3","hex":"#dbdbdb","rgb":[219,219,219],"name":"Snow Block","mat_id":"128","file":"textures\/80_0.png","transparent":false,"opacity":1,"texture":"80_0.png"},"2":{"x":3,"y":"3","z":"2","hex":"#82b3b3","rgb":[130,179,179],"name":"Packed Ice","mat_id":"1652","file":"","transparent":false,"opacity":1,"texture":"174_0.png"},"1":{"x":3,"y":"3","z":"1","hex":"#82b3b3","rgb":[130,179,179],"name":"Packed Ice","mat_id":"1652","file":"","transparent":false,"opacity":1,"texture":"174_0.png"}},"2":{"1":{"x":2,"y":"3","z":"1","hex":"#82b3b3","rgb":[130,179,179],"name":"Packed Ice","mat_id":"1652","file":"","transparent":false,"opacity":1,"texture":"174_0.png"},"2":{"x":2,"y":"3","z":"2","hex":"#82b3b3","rgb":[130,179,179],"name":"Packed Ice","mat_id":"1652","file":"","transparent":false,"opacity":1,"texture":"174_0.png"},"3":{"x":2,"y":"3","z":"3","hex":"#82b3b3","rgb":[130,179,179],"name":"Packed Ice","mat_id":"1652","file":"","transparent":false,"opacity":1,"texture":"174_0.png"},"4":{"x":2,"y":"3","z":"4","hex":"#82b3b3","rgb":[130,179,179],"name":"Packed Ice","mat_id":"1652","file":"","transparent":false,"opacity":1,"texture":"174_0.png"},"5":{"x":2,"y":"3","z":"5","hex":"#82b3b3","rgb":[130,179,179],"name":"Packed Ice","mat_id":"1652","file":"","transparent":false,"opacity":1,"texture":"174_0.png"}},"1":{"2":{"x":1,"y":"3","z":"2","hex":"#82b3b3","rgb":[130,179,179],"name":"Packed Ice","mat_id":"1652","file":"","transparent":false,"opacity":1,"texture":"174_0.png"},"3":{"x":1,"y":"3","z":"3","hex":"#82b3b3","rgb":[130,179,179],"name":"Packed Ice","mat_id":"1652","file":"","transparent":false,"opacity":1,"texture":"174_0.png"},"4":{"x":1,"y":"3","z":"4","hex":"#82b3b3","rgb":[130,179,179],"name":"Packed Ice","mat_id":"1652","file":"","transparent":false,"opacity":1,"texture":"174_0.png"}},"4":{"1":{"x":4,"y":"3","z":"1","hex":"#82b3b3","rgb":[130,179,179],"name":"Packed Ice","mat_id":"1652","file":"","transparent":false,"opacity":1,"texture":"174_0.png"},"2":{"x":4,"y":"3","z":"2","hex":"#82b3b3","rgb":[130,179,179],"name":"Packed Ice","mat_id":"1652","file":"","transparent":false,"opacity":1,"texture":"174_0.png"},"3":{"x":4,"y":"3","z":"3","hex":"#82b3b3","rgb":[130,179,179],"name":"Packed Ice","mat_id":"1652","file":"","transparent":false,"opacity":1,"texture":"174_0.png"},"4":{"x":4,"y":"3","z":"4","hex":"#82b3b3","rgb":[130,179,179],"name":"Packed Ice","mat_id":"1652","file":"","transparent":false,"opacity":1,"texture":"174_0.png"},"5":{"x":4,"y":"3","z":"5","hex":"#82b3b3","rgb":[130,179,179],"name":"Packed Ice","mat_id":"1652","file":"","transparent":false,"opacity":1,"texture":"174_0.png"}}},"4":{"2":{"3":{"x":2,"y":"4","z":"3","hex":"#82b3b3","rgb":[130,179,179],"name":"Packed Ice","mat_id":"1652","file":"","transparent":false,"opacity":1,"texture":"174_0.png"}},"3":{"2":{"x":3,"y":"4","z":"2","hex":"#82b3b3","rgb":[130,179,179],"name":"Packed Ice","mat_id":"1652","file":"","transparent":false,"opacity":1,"texture":"174_0.png"},"3":{"x":3,"y":"4","z":"3","hex":"#dbdbdb","rgb":[219,219,219],"name":"Snow Block","mat_id":"128","file":"textures\/80_0.png","transparent":false,"opacity":1,"texture":"80_0.png"},"4":{"x":3,"y":"4","z":"4","hex":"#82b3b3","rgb":[130,179,179],"name":"Packed Ice","mat_id":"1652","file":"","transparent":false,"opacity":1,"texture":"174_0.png"}},"4":{"3":{"x":4,"y":"4","z":"3","hex":"#82b3b3","rgb":[130,179,179],"name":"Packed Ice","mat_id":"1652","file":"","transparent":false,"opacity":1,"texture":"174_0.png"}}},"5":{"3":{"3":{"x":3,"y":"5","z":"3","hex":"#dbdbdb","rgb":[219,219,219],"name":"Snow Block","mat_id":"128","file":"textures\/80_0.png","transparent":false,"opacity":1,"texture":"80_0.png"}}},"6":{"3":{"2":{"x":3,"y":"6","z":"2","hex":"#82b3b3","rgb":[130,179,179],"name":"Packed Ice","mat_id":"1652","file":"","transparent":false,"opacity":1,"texture":"174_0.png"},"3":{"x":3,"y":"6","z":"3","hex":"#82b3b3","rgb":[130,179,179],"name":"Packed Ice","mat_id":"1652","file":"","transparent":false,"opacity":1,"texture":"174_0.png"}},"2":{"3":{"x":2,"y":"6","z":"3","hex":"#82b3b3","rgb":[130,179,179],"name":"Packed Ice","mat_id":"1652","file":"","transparent":false,"opacity":1,"texture":"174_0.png"}},"4":{"3":{"x":4,"y":"6","z":"3","hex":"#82b3b3","rgb":[130,179,179],"name":"Packed Ice","mat_id":"1652","file":"","transparent":false,"opacity":1,"texture":"174_0.png"}}}}